{
  "object": "list",
  "data": [
    {
      "playerID": "abacon",
      "firstName": "Aaron",
      "lastName": "Bacon",
      "teamID": "revolution",
      "active": false,
      "jerseyNumber": "",
      "year": 2014
    },
    {
      "playerID": "abaker",
      "firstName": "Alex",
      "lastName": "Baker",
      "teamID": "windchill",
      "active": false,
      "jerseyNumber": "",
      "year": 2014
    },
    {
      "playerID": "abarnhart",
      "firstName": "Andy",
      "lastName": "Barnhart",
      "teamID": "mechanix",
      "active": false,
      "jerseyNumber": "",
      "year": 2014
    },
    {
      "playerID": "abertoia",
      "firstName": "Alex",
      "lastName": "Bertoia",
      "teamID": "mechanix",
      "active": false,
      "jerseyNumber": "",
      "year": 2014
    },
    {
      "playerID": "abronstei",
      "firstName": "Adam",
      "lastName": "Bronstein",
      "teamID": "cascades",
      "active": false,
      "jerseyNumber": "",
      "year": 2014
    },
    {
      "playerID": "abrown",
      "firstName": "Andrew",
      "lastName": "Brown",
      "teamID": "radicals",
      "active": false,
      "jerseyNumber": "",
      "year": 2014
    },
    {
      "playerID": "abushek",
      "firstName": "Anthony",
      "lastName": "Bushek",
      "teamID": "phoenix",
      "active": false,
      "jerseyNumber": "",
      "year": 2014
    },
    {
      "playerID": "acava",
      "firstName": "Andy",
      "lastName": "Cava",
      "teamID": "alleycats",
      "active": false,
      "jerseyNumber": "",
      "year": 2014
    },
    {
      "playerID": "acorley",
      "firstName": "Aaron",
      "lastName": "Corley",
      "teamID": "revolution",
      "active": false,
      "jerseyNumber": "",
      "year": 2014
    },
    {
      "playerID": "adavis",
      "firstName": "Aubrey",
      "lastName": "Davis",
      "teamID": "spiders",
      "active": false,
      "jerseyNumber": "",
      "year": 2014
    },
    {
      "playerID": "adelreal",
      "firstName": "Aaron",
      "lastName": "Del Real",
      "teamID": "mechanix",
      "active": false,
      "jerseyNumber": "",
      "year": 2014
    },
    {
      "playerID": "adrews",
      "firstName": "Adam",
      "lastName": "Drews",
      "teamID": "radicals",
      "active": false,
      "jerseyNumber": "",
      "year": 2014
    },
    {
      "playerID": "adrlicawa",
      "firstName": "Alex",
      "lastName": "Drlica-Wagner",
      "teamID": "union",
      "active": false,
      "jerseyNumber": "",
      "year": 2014
    },
    {
      "playerID": "aevangeli",
      "firstName": "Alex",
      "lastName": "Evangelides",
      "teamID": "flamethrowers",
      "active": false,
      "jerseyNumber": "",
      "year": 2014
    },
    {
      "playerID": "afelser",
      "firstName": "Adlai",
      "lastName": "Felser",
      "teamID": "cascades",
      "active": false,
      "jerseyNumber": "",
      "year": 2014
    },
    {
      "playerID": "agenest",
      "firstName": "Antoine",
      "lastName": "Genest",
      "teamID": "royal",
      "active": false,
      "jerseyNumber": "",
      "year": 2014
    },
    {
      "playerID": "ahagen",
      "firstName": "Andrew",
      "lastName": "Hagen",
      "teamID": "flamethrowers",
      "active": false,
      "jerseyNumber": "",
      "year": 2014
    },
    {
      "playerID": "ahuels",
      "firstName": "Alan",
      "lastName": "Huels",
      "teamID": "revolution",
      "active": false,
      "jerseyNumber": "",
      "year": 2014
    },
    {
      "playerID": "ahutton",
      "firstName": "Alex",
      "lastName": "Hutton",
      "teamID": "alleycats",
      "active": false,
      "jerseyNumber": "",
      "year": 2014
    },
    {
      "playerID": "ajacoski",
      "firstName": "AJ",
      "lastName": "Jacoski",
      "teamID": "breeze",
      "active": false,
      "jerseyNumber": "",
      "year": 2014
    },
    {
      "playerID": "ajoye",
      "firstName": "Ashlin",
      "lastName": "Joye",
      "teamID": "spiders",
      "active": false,
      "jerseyNumber": "",
      "year": 2014
    },
    {
      "playerID": "akubinec",
      "firstName": "Andrew",
      "lastName": "Kubinec",
      "teamID": "rush",
      "active": false,
      "jerseyNumber": "",
      "year": 2014
    },
    {
      "playerID": "alien",
      "firstName": "Austin",
      "lastName": "Lien",
      "teamID": "windchill",
      "active": false,
      "jerseyNumber": "",
      "year": 2014
    },
    {
      "playerID": "alucarott",
      "firstName": "Andrew",
      "lastName": "Lucarotti",
      "teamID": "mechanix",
      "active": false,
      "jerseyNumber": "",
      "year": 2014
    },
    {
      "playerID": "alynch",
      "firstName": "Andrew",
      "lastName": "Lynch",
      "teamID": "cascades",
      "active": false,
      "jerseyNumber": "",
      "year": 2014
    },
    {
      "playerID": "ameshnick",
      "firstName": "Andrew",
      "lastName": "Meshnick",
      "teamID": "radicals",
      "active": false,
      "jerseyNumber": "",
      "year": 2014
    },
    {
      "playerID": "anelson",
      "firstName": "AJ",
      "lastName": "Nelson",
      "teamID": "union",
      "active": false,
      "jerseyNumber": "",
      "year": 2014
    },
    {
      "playerID": "anielsen",
      "firstName": "Andy",
      "lastName": "Nielsen",
      "teamID": "union",
      "active": false,
      "jerseyNumber": "",
      "year": 2014
    },
    {
      "playerID": "anord",
      "firstName": "Alex",
      "lastName": "Nord",
      "teamID": "flamethrowers",
      "active": false,
      "jerseyNumber": "",
      "year": 2014
    },
    {
      "playerID": "anorton",
      "firstName": "Alec",
      "lastName": "Norton",
      "teamID": "dragons",
      "active": false,
      "jerseyNumber": "",
      "year": 2014
    },
    {
      "playerID": "araty",
      "firstName": "Adam",
      "lastName": "Raty",
      "teamID": "flamethrowers",
      "active": false,
      "jerseyNumber": "",
      "year": 2014
    },
    {
      "playerID": "areif",
      "firstName": "Adrian",
      "lastName": "Reif",
      "teamID": "radicals",
      "active": false,
      "jerseyNumber": "",
      "year": 2014
    },
    {
      "playerID": "aroberts",
      "firstName": "Aaron",
      "lastName": "Roberts",
      "teamID": "breeze",
      "active": false,
      "jerseyNumber": "",
      "year": 2014
    },
    {
      "playerID": "asheehan",
      "firstName": "Andrew",
      "lastName": "Sheehan",
      "teamID": "union",
      "active": false,
      "jerseyNumber": "",
      "year": 2014
    },
    {
      "playerID": "asmith1",
      "firstName": "Alex",
      "lastName": "Smith",
      "teamID": "mechanix",
      "active": false,
      "jerseyNumber": "",
      "year": 2014
    },
    {
      "playerID": "athorne",
      "firstName": "Alex",
      "lastName": "Thorne",
      "teamID": "breeze",
      "active": false,
      "jerseyNumber": "",
      "year": 2014
    },
    {
      "playerID": "avasilyev",
      "firstName": "Anatoly",
      "lastName": "Vasilyev",
      "teamID": "rush",
      "active": false,
      "jerseyNumber": "",
      "year": 2014
    },
    {
      "playerID": "awadaga",
      "firstName": "Andrew",
      "lastName": "Wadaga",
      "teamID": "mechanix",
      "active": false,
      "jerseyNumber": "",
      "year": 2014
    },
    {
      "playerID": "awatts",
      "firstName": "Andrew",
      "lastName": "Watts",
      "teamID": "rush",
      "active": false,
      "jerseyNumber": "",
      "year": 2014
    },
    {
      "playerID": "ayearwood",
      "firstName": "Adrian",
      "lastName": "Yearwood",
      "teamID": "rush",
      "active": false,
      "jerseyNumber": "",
      "year": 2014
    },
    {
      "playerID": "bawerbuch",
      "firstName": "Brendan",
      "lastName": "Awerbuch",
      "teamID": "empire",
      "active": false,
      "jerseyNumber": "",
      "year": 2014
    },
    {
      "playerID": "bbaker",
      "firstName": "Brian",
      "lastName": "Baker",
      "teamID": "riptide",
      "active": false,
      "jerseyNumber": "",
      "year": 2014
    },
    {
      "playerID": "bblatz",
      "firstName": "Ben",
      "lastName": "Blatz",
      "teamID": "revolution",
      "active": false,
      "jerseyNumber": "",
      "year": 2014
    },
    {
      "playerID": "bbroser",
      "firstName": "Ben",
      "lastName": "Broser",
      "teamID": "phoenix",
      "active": false,
      "jerseyNumber": "",
      "year": 2014
    },
    {
      "playerID": "bdemers",
      "firstName": "Bruno-Pier",
      "lastName": "Demers",
      "teamID": "royal",
      "active": false,
      "jerseyNumber": "",
      "year": 2014
    },
    {
      "playerID": "beverhart",
      "firstName": "Bill",
      "lastName": "Everhart",
      "teamID": "radicals",
      "active": false,
      "jerseyNumber": "",
      "year": 2014
    },
    {
      "playerID": "bfein",
      "firstName": "Brandon",
      "lastName": "Fein",
      "teamID": "flamethrowers",
      "active": false,
      "jerseyNumber": "",
      "year": 2014
    },
    {
      "playerID": "bfeldman",
      "firstName": "Ben",
      "lastName": "Feldman",
      "teamID": "windchill",
      "active": false,
      "jerseyNumber": "",
      "year": 2014
    },
    {
      "playerID": "bfeng",
      "firstName": "Ben",
      "lastName": "Feng",
      "teamID": "breeze",
      "active": false,
      "jerseyNumber": "",
      "year": 2014
    },
    {
      "playerID": "bgerroll",
      "firstName": "Ben",
      "lastName": "Gerroll",
      "teamID": "alleycats",
      "active": false,
      "jerseyNumber": "",
      "year": 2014
    },
    {
      "playerID": "bhart",
      "firstName": "Brian",
      "lastName": "Hart",
      "teamID": "radicals",
      "active": false,
      "jerseyNumber": "",
      "year": 2014
    },
    {
      "playerID": "bhouser",
      "firstName": "Brad",
      "lastName": "Houser",
      "teamID": "cascades",
      "active": false,
      "jerseyNumber": "",
      "year": 2014
    },
    {
      "playerID": "bivers",
      "firstName": "Ben",
      "lastName": "Ivers",
      "teamID": "empire",
      "active": false,
      "jerseyNumber": "",
      "year": 2014
    },
    {
      "playerID": "bjagt",
      "firstName": "Ben",
      "lastName": "Jagt",
      "teamID": "windchill",
      "active": false,
      "jerseyNumber": "",
      "year": 2014
    },
    {
      "playerID": "bjansen",
      "firstName": "Ben",
      "lastName": "Jansen",
      "teamID": "revolution",
      "active": false,
      "jerseyNumber": "",
      "year": 2014
    },
    {
      "playerID": "bjones1",
      "firstName": "Ben",
      "lastName": "Jones",
      "teamID": "lions",
      "active": false,
      "jerseyNumber": "",
      "year": 2014
    },
    {
      "playerID": "bkatz",
      "firstName": "Billy",
      "lastName": "Katz",
      "teamID": "empire",
      "active": false,
      "jerseyNumber": "",
      "year": 2014
    },
    {
      "playerID": "bkeren",
      "firstName": "Benjy",
      "lastName": "Keren",
      "teamID": "radicals",
      "active": false,
      "jerseyNumber": "",
      "year": 2014
    },
    {
      "playerID": "bkibler",
      "firstName": "Brian",
      "lastName": "Kibler",
      "teamID": "dragons",
      "active": false,
      "jerseyNumber": "",
      "year": 2014
    },
    {
      "playerID": "bkittredg",
      "firstName": "Beau",
      "lastName": "Kittredge",
      "teamID": "spiders",
      "active": false,
      "jerseyNumber": "",
      "year": 2014
    },
    {
      "playerID": "bkolinek",
      "firstName": "Brett",
      "lastName": "Kolinek",
      "teamID": "union",
      "active": false,
      "jerseyNumber": "",
      "year": 2014
    },
    {
      "playerID": "blaursen",
      "firstName": "Bjarne",
      "lastName": "Laursen",
      "teamID": "mechanix",
      "active": false,
      "jerseyNumber": "",
      "year": 2014
    },
    {
      "playerID": "blaw",
      "firstName": "Benjamin",
      "lastName": "Law",
      "teamID": "lions",
      "active": false,
      "jerseyNumber": "",
      "year": 2014
    },
    {
      "playerID": "bliu1",
      "firstName": "Bob",
      "lastName": "Liu",
      "teamID": "union",
      "active": false,
      "jerseyNumber": "",
      "year": 2014
    },
    {
      "playerID": "bmagerr",
      "firstName": "Brian",
      "lastName": "Magerr",
      "teamID": "phoenix",
      "active": false,
      "jerseyNumber": "",
      "year": 2014
    },
    {
      "playerID": "bmatis",
      "firstName": "Brandon",
      "lastName": "Matis",
      "teamID": "windchill",
      "active": false,
      "jerseyNumber": "",
      "year": 2014
    },
    {
      "playerID": "bmatzuka",
      "firstName": "Brett",
      "lastName": "Matzuka",
      "teamID": "breeze",
      "active": false,
      "jerseyNumber": "",
      "year": 2014
    },
    {
      "playerID": "bmurphy",
      "firstName": "Ben",
      "lastName": "Murphy",
      "teamID": "mechanix",
      "active": false,
      "jerseyNumber": "",
      "year": 2014
    },
    {
      "playerID": "bnelson",
      "firstName": "Ben",
      "lastName": "Nelson",
      "teamID": "radicals",
      "active": false,
      "jerseyNumber": "68",
      "year": 2014
    },
    {
      "playerID": "bpetersen",
      "firstName": "Brett",
      "lastName": "Petersen",
      "teamID": "spiders",
      "active": false,
      "jerseyNumber": "",
      "year": 2014
    },
    {
      "playerID": "brehmann",
      "firstName": "Ben",
      "lastName": "Rehmann",
      "teamID": "union",
      "active": false,
      "jerseyNumber": "",
      "year": 2014
    },
    {
      "playerID": "bsawyer",
      "firstName": "Brett",
      "lastName": "Sawyer",
      "teamID": "phoenix",
      "active": false,
      "jerseyNumber": "",
      "year": 2014
    },
    {
      "playerID": "bschoenro",
      "firstName": "Brian",
      "lastName": "Schoenrock",
      "teamID": "windchill",
      "active": false,
      "jerseyNumber": "",
      "year": 2014
    },
    {
      "playerID": "bschwalm",
      "firstName": "Brendan",
      "lastName": "Schwalm",
      "teamID": "mechanix",
      "active": false,
      "jerseyNumber": "",
      "year": 2014
    },
    {
      "playerID": "bscott",
      "firstName": "Brad",
      "lastName": "Scott",
      "teamID": "breeze",
      "active": false,
      "jerseyNumber": "",
      "year": 2014
    },
    {
      "playerID": "bsever",
      "firstName": "Ben",
      "lastName": "Sever",
      "teamID": "revolution",
      "active": false,
      "jerseyNumber": "",
      "year": 2014
    },
    {
      "playerID": "bsmith",
      "firstName": "Brodie",
      "lastName": "Smith",
      "teamID": "union",
      "active": false,
      "jerseyNumber": "",
      "year": 2014
    },
    {
      "playerID": "bvanderbu",
      "firstName": "Blake",
      "lastName": "Vanderbush",
      "teamID": "alleycats",
      "active": false,
      "jerseyNumber": "",
      "year": 2014
    },
    {
      "playerID": "bventura",
      "firstName": "Brian",
      "lastName": "Ventura",
      "teamID": "alleycats",
      "active": false,
      "jerseyNumber": "",
      "year": 2014
    },
    {
      "playerID": "caubutbou",
      "firstName": "Cedric",
      "lastName": "Aubut-Boucher",
      "teamID": "royal",
      "active": false,
      "jerseyNumber": "",
      "year": 2014
    },
    {
      "playerID": "cbailey",
      "firstName": "Cam",
      "lastName": "Bailey",
      "teamID": "cascades",
      "active": false,
      "jerseyNumber": "",
      "year": 2014
    },
    {
      "playerID": "cbalch",
      "firstName": "Chris",
      "lastName": "Balch",
      "teamID": "lions",
      "active": false,
      "jerseyNumber": "",
      "year": 2014
    },
    {
      "playerID": "cbariteau",
      "firstName": "Charles",
      "lastName": "Bariteau",
      "teamID": "royal",
      "active": false,
      "jerseyNumber": "",
      "year": 2014
    },
    {
      "playerID": "cbrock",
      "firstName": "Cameron",
      "lastName": "Brock",
      "teamID": "alleycats",
      "active": false,
      "jerseyNumber": "",
      "year": 2014
    },
    {
      "playerID": "ccantone",
      "firstName": "Chuck",
      "lastName": "Cantone",
      "teamID": "royal",
      "active": false,
      "jerseyNumber": "",
      "year": 2014
    },
    {
      "playerID": "ccao",
      "firstName": "Chuck",
      "lastName": "Cao",
      "teamID": "flamethrowers",
      "active": false,
      "jerseyNumber": "",
      "year": 2014
    },
    {
      "playerID": "ccolicchi",
      "firstName": "CJ",
      "lastName": "Colicchio",
      "teamID": "dragons",
      "active": false,
      "jerseyNumber": "",
      "year": 2014
    },
    {
      "playerID": "cdegnan",
      "firstName": "Casey",
      "lastName": "Degnan",
      "teamID": "union",
      "active": false,
      "jerseyNumber": "",
      "year": 2014
    },
    {
      "playerID": "celworth",
      "firstName": "Chris",
      "lastName": "Elworth",
      "teamID": "alleycats",
      "active": false,
      "jerseyNumber": "",
      "year": 2014
    },
    {
      "playerID": "cfarina",
      "firstName": "Chris",
      "lastName": "Farina",
      "teamID": "spiders",
      "active": false,
      "jerseyNumber": "",
      "year": 2014
    },
    {
      "playerID": "cfortin",
      "firstName": "Connor",
      "lastName": "Fortin",
      "teamID": "dragons",
      "active": false,
      "jerseyNumber": "",
      "year": 2014
    },
    {
      "playerID": "cgeppert",
      "firstName": "Cullen",
      "lastName": "Geppert",
      "teamID": "union",
      "active": false,
      "jerseyNumber": "",
      "year": 2014
    },
    {
      "playerID": "ch",
      "firstName": "Craig",
      "lastName": "H",
      "teamID": "lions",
      "active": false,
      "jerseyNumber": "",
      "year": 2014
    },
    {
      "playerID": "chaley",
      "firstName": "Connor",
      "lastName": "Haley",
      "teamID": "revolution",
      "active": false,
      "jerseyNumber": "",
      "year": 2014
    },
    {
      "playerID": "charris",
      "firstName": "Cameron",
      "lastName": "Harris",
      "teamID": "rush",
      "active": false,
      "jerseyNumber": "",
      "year": 2014
    },
    {
      "playerID": "chippman",
      "firstName": "Chuck",
      "lastName": "Hippman",
      "teamID": "cascades",
      "active": false,
      "jerseyNumber": "",
      "year": 2014
    },
    {
      "playerID": "ckocher",
      "firstName": "Chris",
      "lastName": "Kocher",
      "teamID": "breeze",
      "active": false,
      "jerseyNumber": "",
      "year": 2014
    },
    {
      "playerID": "ckosednar",
      "firstName": "Chris",
      "lastName": "Kosednar",
      "teamID": "flamethrowers",
      "active": false,
      "jerseyNumber": "",
      "year": 2014
    },
    {
      "playerID": "clukas",
      "firstName": "Connor",
      "lastName": "Lukas",
      "teamID": "mechanix",
      "active": false,
      "jerseyNumber": "",
      "year": 2014
    },
    {
      "playerID": "cmathieu",
      "firstName": "Christian",
      "lastName": "Mathieu",
      "teamID": "royal",
      "active": false,
      "jerseyNumber": "",
      "year": 2014
    },
    {
      "playerID": "cmiller",
      "firstName": "Clay",
      "lastName": "Miller",
      "teamID": "flamethrowers",
      "active": false,
      "jerseyNumber": "",
      "year": 2014
    },
    {
      "playerID": "cosborn",
      "firstName": "Cole",
      "lastName": "Osborn",
      "teamID": "mechanix",
      "active": false,
      "jerseyNumber": "",
      "year": 2014
    },
    {
      "playerID": "cpowers",
      "firstName": "Chris",
      "lastName": "Powers",
      "teamID": "revolution",
      "active": false,
      "jerseyNumber": "",
      "year": 2014
    },
    {
      "playerID": "cqiu",
      "firstName": "Cecil",
      "lastName": "Qiu",
      "teamID": "flamethrowers",
      "active": false,
      "jerseyNumber": "",
      "year": 2014
    },
    {
      "playerID": "crasmusse",
      "firstName": "Cassidy",
      "lastName": "Rasmussen",
      "teamID": "flamethrowers",
      "active": false,
      "jerseyNumber": "",
      "year": 2014
    },
    {
      "playerID": "cschulze",
      "firstName": "Chris",
      "lastName": "Schulze",
      "teamID": "phoenix",
      "active": false,
      "jerseyNumber": "",
      "year": 2014
    },
    {
      "playerID": "csmith",
      "firstName": "Colin",
      "lastName": "Smith",
      "teamID": "phoenix",
      "active": false,
      "jerseyNumber": "",
      "year": 2014
    },
    {
      "playerID": "cstartzel",
      "firstName": "Casey",
      "lastName": "Startzell",
      "teamID": "phoenix",
      "active": false,
      "jerseyNumber": "",
      "year": 2014
    },
    {
      "playerID": "cvandervo",
      "firstName": "Chris",
      "lastName": "Vandervoort",
      "teamID": "union",
      "active": false,
      "jerseyNumber": "",
      "year": 2014
    },
    {
      "playerID": "dabbott",
      "firstName": "Dave",
      "lastName": "Abbott",
      "teamID": "dragons",
      "active": false,
      "jerseyNumber": "",
      "year": 2014
    },
    {
      "playerID": "danderson",
      "firstName": "Devon",
      "lastName": "Anderson",
      "teamID": "spiders",
      "active": false,
      "jerseyNumber": "",
      "year": 2014
    },
    {
      "playerID": "dbjorkman",
      "firstName": "Danny",
      "lastName": "Bjorkman",
      "teamID": "phoenix",
      "active": false,
      "jerseyNumber": "",
      "year": 2014
    },
    {
      "playerID": "dbrooks",
      "firstName": "David",
      "lastName": "Brooks",
      "teamID": "lions",
      "active": false,
      "jerseyNumber": "",
      "year": 2014
    },
    {
      "playerID": "dbutler",
      "firstName": "Daniel",
      "lastName": "Butler",
      "teamID": "alleycats",
      "active": false,
      "jerseyNumber": "",
      "year": 2014
    },
    {
      "playerID": "dchen1",
      "firstName": "Dafeng",
      "lastName": "Chen",
      "teamID": "mechanix",
      "active": false,
      "jerseyNumber": "",
      "year": 2014
    },
    {
      "playerID": "ddanks",
      "firstName": "David",
      "lastName": "Danks",
      "teamID": "mechanix",
      "active": false,
      "jerseyNumber": "",
      "year": 2014
    },
    {
      "playerID": "ddennin",
      "firstName": "Danny",
      "lastName": "Dennin",
      "teamID": "breeze",
      "active": false,
      "jerseyNumber": "",
      "year": 2014
    },
    {
      "playerID": "ddunbar",
      "firstName": "Dana",
      "lastName": "Dunbar",
      "teamID": "cascades",
      "active": false,
      "jerseyNumber": "",
      "year": 2014
    },
    {
      "playerID": "dfenton",
      "firstName": "Derek",
      "lastName": "Fenton",
      "teamID": "riptide",
      "active": false,
      "jerseyNumber": "",
      "year": 2014
    },
    {
      "playerID": "dferraro",
      "firstName": "David",
      "lastName": "Ferraro",
      "teamID": "dragons",
      "active": false,
      "jerseyNumber": "",
      "year": 2014
    },
    {
      "playerID": "dgillick",
      "firstName": "Dan",
      "lastName": "Gillick",
      "teamID": "flamethrowers",
      "active": false,
      "jerseyNumber": "",
      "year": 2014
    },
    {
      "playerID": "dgreeley",
      "firstName": "Daniel",
      "lastName": "Greeley",
      "teamID": "cascades",
      "active": false,
      "jerseyNumber": "",
      "year": 2014
    },
    {
      "playerID": "dhampson",
      "firstName": "David",
      "lastName": "Hampson",
      "teamID": "phoenix",
      "active": false,
      "jerseyNumber": "",
      "year": 2014
    },
    {
      "playerID": "dhochhalt",
      "firstName": "David",
      "lastName": "Hochhalter",
      "teamID": "mechanix",
      "active": false,
      "jerseyNumber": "",
      "year": 2014
    },
    {
      "playerID": "dhunt",
      "firstName": "Danny",
      "lastName": "Hunt",
      "teamID": "windchill",
      "active": false,
      "jerseyNumber": "",
      "year": 2014
    },
    {
      "playerID": "dhunt1",
      "firstName": "Daniel",
      "lastName": "Hunt",
      "teamID": "mechanix",
      "active": false,
      "jerseyNumber": "",
      "year": 2014
    },
    {
      "playerID": "dkelly",
      "firstName": "Dave",
      "lastName": "Kelly",
      "teamID": "phoenix",
      "active": false,
      "jerseyNumber": "",
      "year": 2014
    },
    {
      "playerID": "dlockhart",
      "firstName": "Dane",
      "lastName": "Lockhart",
      "teamID": "alleycats",
      "active": false,
      "jerseyNumber": "",
      "year": 2014
    },
    {
      "playerID": "dmccune",
      "firstName": "Dan",
      "lastName": "McCune",
      "teamID": "dragons",
      "active": false,
      "jerseyNumber": "",
      "year": 2014
    },
    {
      "playerID": "dmiesen",
      "firstName": "Dan",
      "lastName": "Miesen",
      "teamID": "windchill",
      "active": false,
      "jerseyNumber": "",
      "year": 2014
    },
    {
      "playerID": "dmiller1",
      "firstName": "Dan",
      "lastName": "Miller",
      "teamID": "windchill",
      "active": false,
      "jerseyNumber": "",
      "year": 2014
    },
    {
      "playerID": "dnaruo",
      "firstName": "Daniel",
      "lastName": "Naruo",
      "teamID": "spiders",
      "active": false,
      "jerseyNumber": "",
      "year": 2014
    },
    {
      "playerID": "dolsen",
      "firstName": "Dane",
      "lastName": "Olsen",
      "teamID": "union",
      "active": false,
      "jerseyNumber": "",
      "year": 2014
    },
    {
      "playerID": "drooffene",
      "firstName": "Dustin",
      "lastName": "Rooffener",
      "teamID": "windchill",
      "active": false,
      "jerseyNumber": "",
      "year": 2014
    },
    {
      "playerID": "drowan",
      "firstName": "Dan",
      "lastName": "Rowan",
      "teamID": "radicals",
      "active": false,
      "jerseyNumber": "",
      "year": 2014
    },
    {
      "playerID": "dschleich",
      "firstName": "David",
      "lastName": "Schleicher",
      "teamID": "radicals",
      "active": false,
      "jerseyNumber": "",
      "year": 2014
    },
    {
      "playerID": "dselwyn",
      "firstName": "Daniel",
      "lastName": "Selwyn",
      "teamID": "breeze",
      "active": false,
      "jerseyNumber": "",
      "year": 2014
    },
    {
      "playerID": "dshirley",
      "firstName": "David",
      "lastName": "Shirley",
      "teamID": "windchill",
      "active": false,
      "jerseyNumber": "",
      "year": 2014
    },
    {
      "playerID": "dshonk",
      "firstName": "Danny",
      "lastName": "Shonk",
      "teamID": "revolution",
      "active": false,
      "jerseyNumber": "",
      "year": 2014
    },
    {
      "playerID": "dstenclik",
      "firstName": "Doug",
      "lastName": "Stenclik",
      "teamID": "lions",
      "active": false,
      "jerseyNumber": "",
      "year": 2014
    },
    {
      "playerID": "dsullivan",
      "firstName": "Dustin",
      "lastName": "Sullivan",
      "teamID": "phoenix",
      "active": false,
      "jerseyNumber": "",
      "year": 2014
    },
    {
      "playerID": "dtriplett",
      "firstName": "Donovan",
      "lastName": "Triplett",
      "teamID": "alleycats",
      "active": false,
      "jerseyNumber": "",
      "year": 2014
    },
    {
      "playerID": "durbino",
      "firstName": "Doug",
      "lastName": "Urbino",
      "teamID": "dragons",
      "active": false,
      "jerseyNumber": "",
      "year": 2014
    },
    {
      "playerID": "dvalentin",
      "firstName": "David",
      "lastName": "Valentine-Elam",
      "teamID": "alleycats",
      "active": false,
      "jerseyNumber": "",
      "year": 2014
    },
    {
      "playerID": "dwenzel",
      "firstName": "David",
      "lastName": "Wenzel",
      "teamID": "windchill",
      "active": false,
      "jerseyNumber": "",
      "year": 2014
    },
    {
      "playerID": "dwhitehea",
      "firstName": "Davis",
      "lastName": "Whitehead",
      "teamID": "radicals",
      "active": false,
      "jerseyNumber": "",
      "year": 2014
    },
    {
      "playerID": "dwilliams1",
      "firstName": "Dan",
      "lastName": "Williams",
      "teamID": "union",
      "active": false,
      "jerseyNumber": "",
      "year": 2014
    },
    {
      "playerID": "dwiseman",
      "firstName": "Dave",
      "lastName": "Wiseman",
      "teamID": "radicals",
      "active": false,
      "jerseyNumber": "",
      "year": 2014
    },
    {
      "playerID": "dwu",
      "firstName": "Darren",
      "lastName": "Wu",
      "teamID": "riptide",
      "active": false,
      "jerseyNumber": "",
      "year": 2014
    },
    {
      "playerID": "dyan",
      "firstName": "Derek",
      "lastName": "Yan",
      "teamID": "empire",
      "active": false,
      "jerseyNumber": "",
      "year": 2014
    },
    {
      "playerID": "ebemis",
      "firstName": "Eliot",
      "lastName": "Bemis",
      "teamID": "empire",
      "active": false,
      "jerseyNumber": "",
      "year": 2014
    },
    {
      "playerID": "eblanchar",
      "firstName": "Eric",
      "lastName": "Blanchard",
      "teamID": "rush",
      "active": false,
      "jerseyNumber": "",
      "year": 2014
    },
    {
      "playerID": "econverse",
      "firstName": "Eric",
      "lastName": "Converse",
      "teamID": "revolution",
      "active": false,
      "jerseyNumber": "",
      "year": 2014
    },
    {
      "playerID": "edion",
      "firstName": "Eric",
      "lastName": "Dion",
      "teamID": "royal",
      "active": false,
      "jerseyNumber": "",
      "year": 2014
    },
    {
      "playerID": "egreenwoo",
      "firstName": "Eric",
      "lastName": "Greenwood",
      "teamID": "flamethrowers",
      "active": false,
      "jerseyNumber": "",
      "year": 2014
    },
    {
      "playerID": "eguo",
      "firstName": "Edward",
      "lastName": "Guo",
      "teamID": "riptide",
      "active": false,
      "jerseyNumber": "",
      "year": 2014
    },
    {
      "playerID": "ehubbard",
      "firstName": "Eric",
      "lastName": "Hubbard",
      "teamID": "mechanix",
      "active": false,
      "jerseyNumber": "",
      "year": 2014
    },
    {
      "playerID": "ehughes",
      "firstName": "Evan",
      "lastName": "Hughes",
      "teamID": "mechanix",
      "active": false,
      "jerseyNumber": "",
      "year": 2014
    },
    {
      "playerID": "ehunter",
      "firstName": "Erik",
      "lastName": "Hunter",
      "teamID": "riptide",
      "active": false,
      "jerseyNumber": "",
      "year": 2014
    },
    {
      "playerID": "ejanin",
      "firstName": "Eli",
      "lastName": "Janin",
      "teamID": "flamethrowers",
      "active": false,
      "jerseyNumber": "",
      "year": 2014
    },
    {
      "playerID": "ejohnson",
      "firstName": "Eric",
      "lastName": "Johnson",
      "teamID": "alleycats",
      "active": false,
      "jerseyNumber": "",
      "year": 2014
    },
    {
      "playerID": "ejohnson1",
      "firstName": "Eric",
      "lastName": "EJ Johnson",
      "teamID": "windchill",
      "active": false,
      "jerseyNumber": "",
      "year": 2014
    },
    {
      "playerID": "ekerns",
      "firstName": "Eli",
      "lastName": "Kerns",
      "teamID": "spiders",
      "active": false,
      "jerseyNumber": "",
      "year": 2014
    },
    {
      "playerID": "eklein",
      "firstName": "Evan",
      "lastName": "Klein",
      "teamID": "cascades",
      "active": false,
      "jerseyNumber": "",
      "year": 2014
    },
    {
      "playerID": "elim1",
      "firstName": "Einer",
      "lastName": "Lim",
      "teamID": "riptide",
      "active": false,
      "jerseyNumber": "",
      "year": 2014
    },
    {
      "playerID": "emack",
      "firstName": "Eddie",
      "lastName": "Mack",
      "teamID": "revolution",
      "active": false,
      "jerseyNumber": "",
      "year": 2014
    },
    {
      "playerID": "emeccarel",
      "firstName": "Evan",
      "lastName": "Meccarello",
      "teamID": "dragons",
      "active": false,
      "jerseyNumber": "",
      "year": 2014
    },
    {
      "playerID": "epeck",
      "firstName": "Ethan",
      "lastName": "Peck",
      "teamID": "phoenix",
      "active": false,
      "jerseyNumber": "",
      "year": 2014
    },
    {
      "playerID": "epinto",
      "firstName": "Eamon",
      "lastName": "Pinto",
      "teamID": "rush",
      "active": false,
      "jerseyNumber": "",
      "year": 2014
    },
    {
      "playerID": "estamant",
      "firstName": "Eric",
      "lastName": "St-Amant",
      "teamID": "royal",
      "active": false,
      "jerseyNumber": "",
      "year": 2014
    },
    {
      "playerID": "fbredard",
      "firstName": "Fred",
      "lastName": "Bredard",
      "teamID": "royal",
      "active": false,
      "jerseyNumber": "",
      "year": 2014
    },
    {
      "playerID": "fchialvo",
      "firstName": "Federico",
      "lastName": "Chialvo",
      "teamID": "spiders",
      "active": false,
      "jerseyNumber": "",
      "year": 2014
    },
    {
      "playerID": "fdaigle",
      "firstName": "F\u00e9lix-Antoine",
      "lastName": "Daigle",
      "teamID": "royal",
      "active": false,
      "jerseyNumber": "",
      "year": 2014
    },
    {
      "playerID": "fharris",
      "firstName": "Frank",
      "lastName": "Harris",
      "teamID": "phoenix",
      "active": false,
      "jerseyNumber": "",
      "year": 2014
    },
    {
      "playerID": "fhezera",
      "firstName": "Francisco",
      "lastName": "Hezera",
      "teamID": "breeze",
      "active": false,
      "jerseyNumber": "",
      "year": 2014
    },
    {
      "playerID": "fhotte",
      "firstName": "Francois-Xavier",
      "lastName": "Hotte",
      "teamID": "royal",
      "active": false,
      "jerseyNumber": "",
      "year": 2014
    },
    {
      "playerID": "fmogollon",
      "firstName": "Francisco",
      "lastName": "Mogollon",
      "teamID": "riptide",
      "active": false,
      "jerseyNumber": "",
      "year": 2014
    },
    {
      "playerID": "fvallee",
      "firstName": "Francis",
      "lastName": "Vall\u00e9e",
      "teamID": "royal",
      "active": false,
      "jerseyNumber": "",
      "year": 2014
    },
    {
      "playerID": "gaponte",
      "firstName": "Gyorgy",
      "lastName": "Aponte",
      "teamID": "riptide",
      "active": false,
      "jerseyNumber": "",
      "year": 2014
    },
    {
      "playerID": "gcastano",
      "firstName": "Gustavo",
      "lastName": "Castano",
      "teamID": "royal",
      "active": false,
      "jerseyNumber": "",
      "year": 2014
    },
    {
      "playerID": "gcohen",
      "firstName": "Greg",
      "lastName": "Cohen",
      "teamID": "spiders",
      "active": false,
      "jerseyNumber": "",
      "year": 2014
    },
    {
      "playerID": "ggarbern",
      "firstName": "Greg",
      "lastName": "Garbern",
      "teamID": "cascades",
      "active": false,
      "jerseyNumber": "",
      "year": 2014
    },
    {
      "playerID": "ghage",
      "firstName": "Gabriel",
      "lastName": "Hage",
      "teamID": "dragons",
      "active": false,
      "jerseyNumber": "",
      "year": 2014
    },
    {
      "playerID": "gharrison",
      "firstName": "Gord",
      "lastName": "Harrison",
      "teamID": "rush",
      "active": false,
      "jerseyNumber": "",
      "year": 2014
    },
    {
      "playerID": "ghughesst",
      "firstName": "George",
      "lastName": "Hughes-Strange",
      "teamID": "union",
      "active": false,
      "jerseyNumber": "",
      "year": 2014
    },
    {
      "playerID": "glandon",
      "firstName": "Graham",
      "lastName": "Landon",
      "teamID": "riptide",
      "active": false,
      "jerseyNumber": "",
      "year": 2014
    },
    {
      "playerID": "gledonne",
      "firstName": "Gary",
      "lastName": "LeDonne",
      "teamID": "union",
      "active": false,
      "jerseyNumber": "",
      "year": 2014
    },
    {
      "playerID": "gmarliave",
      "firstName": "Greg",
      "lastName": "Marliave",
      "teamID": "flamethrowers",
      "active": false,
      "jerseyNumber": "",
      "year": 2014
    },
    {
      "playerID": "gmonfette",
      "firstName": "Gabriel",
      "lastName": "Monfette",
      "teamID": "royal",
      "active": false,
      "jerseyNumber": "",
      "year": 2014
    },
    {
      "playerID": "gpowell",
      "firstName": "Geoff",
      "lastName": "Powell",
      "teamID": "rush",
      "active": false,
      "jerseyNumber": "",
      "year": 2014
    },
    {
      "playerID": "gserednes",
      "firstName": "Geoff",
      "lastName": "Serednesky",
      "teamID": "union",
      "active": false,
      "jerseyNumber": "",
      "year": 2014
    },
    {
      "playerID": "gsing",
      "firstName": "Gavin",
      "lastName": "Sing",
      "teamID": "cascades",
      "active": false,
      "jerseyNumber": "",
      "year": 2014
    },
    {
      "playerID": "gslover",
      "firstName": "Greg",
      "lastName": "Slover",
      "teamID": "union",
      "active": false,
      "jerseyNumber": "",
      "year": 2014
    },
    {
      "playerID": "gvoelling",
      "firstName": "George",
      "lastName": "Voellinger",
      "teamID": "lions",
      "active": false,
      "jerseyNumber": "",
      "year": 2014
    },
    {
      "playerID": "gwakeman",
      "firstName": "Greg",
      "lastName": "Wakeman",
      "teamID": "dragons",
      "active": false,
      "jerseyNumber": "",
      "year": 2014
    },
    {
      "playerID": "gzukowski",
      "firstName": "Grant",
      "lastName": "Zukowski",
      "teamID": "cascades",
      "active": false,
      "jerseyNumber": "",
      "year": 2014
    },
    {
      "playerID": "ibryant",
      "firstName": "Isaiah",
      "lastName": "Bryant",
      "teamID": "empire",
      "active": false,
      "jerseyNumber": "",
      "year": 2014
    },
    {
      "playerID": "iconley",
      "firstName": "Isaac",
      "lastName": "Conley",
      "teamID": "lions",
      "active": false,
      "jerseyNumber": "",
      "year": 2014
    },
    {
      "playerID": "idavis",
      "firstName": "Isaac",
      "lastName": "Davis",
      "teamID": "cascades",
      "active": false,
      "jerseyNumber": "",
      "year": 2014
    },
    {
      "playerID": "idipace",
      "firstName": "Ian",
      "lastName": "Dipace",
      "teamID": "dragons",
      "active": false,
      "jerseyNumber": "",
      "year": 2014
    },
    {
      "playerID": "imasekkel",
      "firstName": "Isaiah",
      "lastName": "Masek-Kelly",
      "teamID": "rush",
      "active": false,
      "jerseyNumber": "",
      "year": 2014
    },
    {
      "playerID": "isaul",
      "firstName": "Isaac",
      "lastName": "Saul",
      "teamID": "empire",
      "active": false,
      "jerseyNumber": "",
      "year": 2014
    },
    {
      "playerID": "jabela",
      "firstName": "John",
      "lastName": "Abela",
      "teamID": "mechanix",
      "active": false,
      "jerseyNumber": "",
      "year": 2014
    },
    {
      "playerID": "jallen",
      "firstName": "Justin",
      "lastName": "Allen",
      "teamID": "empire",
      "active": false,
      "jerseyNumber": "",
      "year": 2014
    },
    {
      "playerID": "jbabbino",
      "firstName": "Joe",
      "lastName": "Babbino",
      "teamID": "empire",
      "active": false,
      "jerseyNumber": "",
      "year": 2014
    },
    {
      "playerID": "jbain",
      "firstName": "Jonathan",
      "lastName": "Bain",
      "teamID": "dragons",
      "active": true,
      "jerseyNumber": null,
      "year": 2014
    },
    {
      "playerID": "jbajwa",
      "firstName": "Jarnail",
      "lastName": "Bajwa",
      "teamID": "breeze",
      "active": false,
      "jerseyNumber": "",
      "year": 2014
    },
    {
      "playerID": "jbecker",
      "firstName": "Joe",
      "lastName": "Becker",
      "teamID": "dragons",
      "active": false,
      "jerseyNumber": "",
      "year": 2014
    },
    {
      "playerID": "jbergen",
      "firstName": "John",
      "lastName": "Bergen",
      "teamID": "spiders",
      "active": false,
      "jerseyNumber": "",
      "year": 2014
    },
    {
      "playerID": "jbesser",
      "firstName": "Joseph",
      "lastName": "Besser",
      "teamID": "mechanix",
      "active": false,
      "jerseyNumber": "",
      "year": 2014
    },
    {
      "playerID": "jboucher",
      "firstName": "Jerome",
      "lastName": "Boucher",
      "teamID": "royal",
      "active": false,
      "jerseyNumber": "",
      "year": 2014
    },
    {
      "playerID": "jbudnik",
      "firstName": "Jimmy",
      "lastName": "Budnik",
      "teamID": "lions",
      "active": false,
      "jerseyNumber": "",
      "year": 2014
    },
    {
      "playerID": "jcari",
      "firstName": "Joey",
      "lastName": "Cari",
      "teamID": "alleycats",
      "active": false,
      "jerseyNumber": "",
      "year": 2014
    },
    {
      "playerID": "jchampagn",
      "firstName": "Jean-Levy",
      "lastName": "Champagne",
      "teamID": "royal",
      "active": false,
      "jerseyNumber": "",
      "year": 2014
    },
    {
      "playerID": "jcheek",
      "firstName": "Jason",
      "lastName": "Cheek",
      "teamID": "alleycats",
      "active": false,
      "jerseyNumber": "",
      "year": 2014
    },
    {
      "playerID": "jcoleman",
      "firstName": "Jake",
      "lastName": "Coleman",
      "teamID": "flamethrowers",
      "active": false,
      "jerseyNumber": "",
      "year": 2014
    },
    {
      "playerID": "jdrescher",
      "firstName": "Jay",
      "lastName": "Drescher",
      "teamID": "windchill",
      "active": false,
      "jerseyNumber": "",
      "year": 2014
    },
    {
      "playerID": "jfiala",
      "firstName": "James",
      "lastName": "Fiala",
      "teamID": "lions",
      "active": false,
      "jerseyNumber": "",
      "year": 2014
    },
    {
      "playerID": "jgaynor",
      "firstName": "Jon",
      "lastName": "Gaynor",
      "teamID": "windchill",
      "active": false,
      "jerseyNumber": "",
      "year": 2014
    },
    {
      "playerID": "jgroess",
      "firstName": "John",
      "lastName": "Groess",
      "teamID": "windchill",
      "active": false,
      "jerseyNumber": "",
      "year": 2014
    },
    {
      "playerID": "jhau",
      "firstName": "Jacky",
      "lastName": "Hau",
      "teamID": "rush",
      "active": false,
      "jerseyNumber": "",
      "year": 2014
    },
    {
      "playerID": "jhelton",
      "firstName": "Jonathan",
      "lastName": "Helton",
      "teamID": "union",
      "active": false,
      "jerseyNumber": "",
      "year": 2014
    },
    {
      "playerID": "jhemmesch",
      "firstName": "Josh",
      "lastName": "Hemmesch",
      "teamID": "windchill",
      "active": false,
      "jerseyNumber": "",
      "year": 2014
    },
    {
      "playerID": "jhron",
      "firstName": "James",
      "lastName": "Hron",
      "teamID": "windchill",
      "active": false,
      "jerseyNumber": "",
      "year": 2014
    },
    {
      "playerID": "jjaskiewi",
      "firstName": "Jason",
      "lastName": "Jaskiewicz",
      "teamID": "mechanix",
      "active": false,
      "jerseyNumber": "",
      "year": 2014
    },
    {
      "playerID": "jkiel",
      "firstName": "Jeff",
      "lastName": "Kiel",
      "teamID": "phoenix",
      "active": false,
      "jerseyNumber": "",
      "year": 2014
    },
    {
      "playerID": "jkingsley",
      "firstName": "Jack",
      "lastName": "Kingsley",
      "teamID": "lions",
      "active": false,
      "jerseyNumber": "",
      "year": 2014
    },
    {
      "playerID": "jklaassen",
      "firstName": "John",
      "lastName": "Klaassen",
      "teamID": "cascades",
      "active": false,
      "jerseyNumber": "",
      "year": 2014
    },
    {
      "playerID": "jklane",
      "firstName": "Josh",
      "lastName": "Klane",
      "teamID": "windchill",
      "active": false,
      "jerseyNumber": "",
      "year": 2014
    },
    {
      "playerID": "jkolb",
      "firstName": "John",
      "lastName": "Kolb",
      "teamID": "union",
      "active": false,
      "jerseyNumber": "",
      "year": 2014
    },
    {
      "playerID": "jkula",
      "firstName": "Jeff",
      "lastName": "Kula",
      "teamID": "revolution",
      "active": false,
      "jerseyNumber": "",
      "year": 2014
    },
    {
      "playerID": "jlieberma",
      "firstName": "Jesse",
      "lastName": "Lieberman",
      "teamID": "empire",
      "active": false,
      "jerseyNumber": "",
      "year": 2014
    },
    {
      "playerID": "jlindquis",
      "firstName": "Jeff",
      "lastName": "Lindquist",
      "teamID": "rush",
      "active": false,
      "jerseyNumber": "",
      "year": 2014
    },
    {
      "playerID": "jlu",
      "firstName": "Jasper",
      "lastName": "Lu",
      "teamID": "riptide",
      "active": false,
      "jerseyNumber": "",
      "year": 2014
    },
    {
      "playerID": "jmaldonad",
      "firstName": "Jose",
      "lastName": "Maldonado",
      "teamID": "breeze",
      "active": false,
      "jerseyNumber": "",
      "year": 2014
    },
    {
      "playerID": "jmartin",
      "firstName": "Jonathan",
      "lastName": "Martin",
      "teamID": "rush",
      "active": false,
      "jerseyNumber": "",
      "year": 2014
    },
    {
      "playerID": "jmeron",
      "firstName": "Jaret",
      "lastName": "Meron",
      "teamID": "rush",
      "active": false,
      "jerseyNumber": "",
      "year": 2014
    },
    {
      "playerID": "jmozloom",
      "firstName": "Joe",
      "lastName": "Mozloom",
      "teamID": "revolution",
      "active": false,
      "jerseyNumber": "",
      "year": 2014
    },
    {
      "playerID": "jnorris",
      "firstName": "Josh",
      "lastName": "Norris",
      "teamID": "breeze",
      "active": false,
      "jerseyNumber": "",
      "year": 2014
    },
    {
      "playerID": "jouellett",
      "firstName": "Joe",
      "lastName": "Ouellette",
      "teamID": "empire",
      "active": false,
      "jerseyNumber": "",
      "year": 2014
    },
    {
      "playerID": "jpalumbo",
      "firstName": "Jonathan",
      "lastName": "Palumbo",
      "teamID": "phoenix",
      "active": false,
      "jerseyNumber": "",
      "year": 2014
    },
    {
      "playerID": "jpayne",
      "firstName": "Jared",
      "lastName": "Payne",
      "teamID": "alleycats",
      "active": false,
      "jerseyNumber": "",
      "year": 2014
    },
    {
      "playerID": "jperez",
      "firstName": "Jaime",
      "lastName": "Perez",
      "teamID": "empire",
      "active": false,
      "jerseyNumber": "",
      "year": 2014
    },
    {
      "playerID": "jpressimo",
      "firstName": "Jon",
      "lastName": "Pressimone",
      "teamID": "breeze",
      "active": false,
      "jerseyNumber": "",
      "year": 2014
    },
    {
      "playerID": "jquandt",
      "firstName": "John",
      "lastName": "Quandt",
      "teamID": "cascades",
      "active": false,
      "jerseyNumber": "",
      "year": 2014
    },
    {
      "playerID": "jrhyne",
      "firstName": "Jordan",
      "lastName": "Rhyne",
      "teamID": "revolution",
      "active": false,
      "jerseyNumber": "",
      "year": 2014
    },
    {
      "playerID": "jriopel",
      "firstName": "Jean-Philippe",
      "lastName": "Riopel",
      "teamID": "royal",
      "active": false,
      "jerseyNumber": "",
      "year": 2014
    },
    {
      "playerID": "jroush",
      "firstName": "James",
      "lastName": "Roush",
      "teamID": "union",
      "active": false,
      "jerseyNumber": "",
      "year": 2014
    },
    {
      "playerID": "jsantosus",
      "firstName": "Joe",
      "lastName": "Santosus",
      "teamID": "empire",
      "active": false,
      "jerseyNumber": "",
      "year": 2014
    },
    {
      "playerID": "jscullion",
      "firstName": "Jadon",
      "lastName": "Scullion",
      "teamID": "radicals",
      "active": false,
      "jerseyNumber": "",
      "year": 2014
    },
    {
      "playerID": "jsellers",
      "firstName": "Jeremy",
      "lastName": "Sellers",
      "teamID": "lions",
      "active": false,
      "jerseyNumber": "",
      "year": 2014
    },
    {
      "playerID": "jsiemer",
      "firstName": "John",
      "lastName": "Siemer",
      "teamID": "revolution",
      "active": false,
      "jerseyNumber": "",
      "year": 2014
    },
    {
      "playerID": "jsilverma",
      "firstName": "Jeffrey",
      "lastName": "Silverman",
      "teamID": "spiders",
      "active": false,
      "jerseyNumber": "",
      "year": 2014
    },
    {
      "playerID": "jsolis",
      "firstName": "Justin",
      "lastName": "Solis",
      "teamID": "breeze",
      "active": false,
      "jerseyNumber": "",
      "year": 2014
    },
    {
      "playerID": "jstaron",
      "firstName": "Jon",
      "lastName": "Staron",
      "teamID": "windchill",
      "active": false,
      "jerseyNumber": "",
      "year": 2014
    },
    {
      "playerID": "jstone",
      "firstName": "Jon",
      "lastName": "Stone",
      "teamID": "breeze",
      "active": false,
      "jerseyNumber": "",
      "year": 2014
    },
    {
      "playerID": "jsullivan",
      "firstName": "Joe",
      "lastName": "Sullivan",
      "teamID": "mechanix",
      "active": false,
      "jerseyNumber": "",
      "year": 2014
    },
    {
      "playerID": "jtan",
      "firstName": "Joshua",
      "lastName": "Tan",
      "teamID": "riptide",
      "active": false,
      "jerseyNumber": "",
      "year": 2014
    },
    {
      "playerID": "jthompson",
      "firstName": "Joe",
      "lastName": "Thompson",
      "teamID": "dragons",
      "active": false,
      "jerseyNumber": "",
      "year": 2014
    },
    {
      "playerID": "jwiley",
      "firstName": "Jordan",
      "lastName": "Wiley",
      "teamID": "phoenix",
      "active": false,
      "jerseyNumber": "",
      "year": 2014
    },
    {
      "playerID": "jwilson",
      "firstName": "Joshua",
      "lastName": "Wilson",
      "teamID": "radicals",
      "active": false,
      "jerseyNumber": "",
      "year": 2014
    },
    {
      "playerID": "jyoder",
      "firstName": "Jason",
      "lastName": "Yoder",
      "teamID": "alleycats",
      "active": false,
      "jerseyNumber": "",
      "year": 2014
    },
    {
      "playerID": "jyun",
      "firstName": "Jason",
      "lastName": "Yun",
      "teamID": "flamethrowers",
      "active": false,
      "jerseyNumber": "",
      "year": 2014
    },
    {
      "playerID": "kaha",
      "firstName": "Kevin",
      "lastName": "Aha",
      "teamID": "spiders",
      "active": false,
      "jerseyNumber": "",
      "year": 2014
    },
    {
      "playerID": "kalexande",
      "firstName": "Kelsen",
      "lastName": "Alexander",
      "teamID": "radicals",
      "active": false,
      "jerseyNumber": "",
      "year": 2014
    },
    {
      "playerID": "kbaumann",
      "firstName": "Kevin",
      "lastName": "Baumann",
      "teamID": "revolution",
      "active": false,
      "jerseyNumber": "",
      "year": 2014
    },
    {
      "playerID": "kbrown",
      "firstName": "Kevin",
      "lastName": "Brown",
      "teamID": "radicals",
      "active": false,
      "jerseyNumber": "",
      "year": 2014
    },
    {
      "playerID": "kcocks",
      "firstName": "Kevin",
      "lastName": "Cocks",
      "teamID": "spiders",
      "active": false,
      "jerseyNumber": "",
      "year": 2014
    },
    {
      "playerID": "kcox",
      "firstName": "Kyle",
      "lastName": "Cox",
      "teamID": "alleycats",
      "active": false,
      "jerseyNumber": "",
      "year": 2014
    },
    {
      "playerID": "kdziak",
      "firstName": "KJ",
      "lastName": "Dziak",
      "teamID": "dragons",
      "active": false,
      "jerseyNumber": "",
      "year": 2014
    },
    {
      "playerID": "kfrisch",
      "firstName": "Kenny",
      "lastName": "Frisch",
      "teamID": "lions",
      "active": false,
      "jerseyNumber": "",
      "year": 2014
    },
    {
      "playerID": "kgarner",
      "firstName": "Keith",
      "lastName": "Garner",
      "teamID": "radicals",
      "active": false,
      "jerseyNumber": "",
      "year": 2014
    },
    {
      "playerID": "kgibson",
      "firstName": "Kurt",
      "lastName": "Gibson",
      "teamID": "spiders",
      "active": false,
      "jerseyNumber": "",
      "year": 2014
    },
    {
      "playerID": "kgill",
      "firstName": "Kyle",
      "lastName": "Gill",
      "teamID": "windchill",
      "active": false,
      "jerseyNumber": "",
      "year": 2014
    },
    {
      "playerID": "kgroulx",
      "firstName": "Kevin",
      "lastName": "Groulx",
      "teamID": "royal",
      "active": false,
      "jerseyNumber": "",
      "year": 2014
    },
    {
      "playerID": "khanzel",
      "firstName": "Kevin",
      "lastName": "Hanzel",
      "teamID": "revolution",
      "active": false,
      "jerseyNumber": "",
      "year": 2014
    },
    {
      "playerID": "khood",
      "firstName": "Kenji",
      "lastName": "Hood",
      "teamID": "lions",
      "active": false,
      "jerseyNumber": "",
      "year": 2014
    },
    {
      "playerID": "khorgan",
      "firstName": "Kevin",
      "lastName": "Horgan",
      "teamID": "rush",
      "active": false,
      "jerseyNumber": "",
      "year": 2014
    },
    {
      "playerID": "kkelly1",
      "firstName": "Kevin",
      "lastName": "Kelly",
      "teamID": "union",
      "active": false,
      "jerseyNumber": "",
      "year": 2014
    },
    {
      "playerID": "kkula",
      "firstName": "Kevin",
      "lastName": "Kula",
      "teamID": "revolution",
      "active": false,
      "jerseyNumber": "",
      "year": 2014
    },
    {
      "playerID": "klewis",
      "firstName": "Ky",
      "lastName": "Lewis",
      "teamID": "cascades",
      "active": false,
      "jerseyNumber": "",
      "year": 2014
    },
    {
      "playerID": "kloiseau",
      "firstName": "Karl",
      "lastName": "Loiseau",
      "teamID": "rush",
      "active": false,
      "jerseyNumber": "",
      "year": 2014
    },
    {
      "playerID": "klore",
      "firstName": "Kevin",
      "lastName": "Lore",
      "teamID": "riptide",
      "active": false,
      "jerseyNumber": "",
      "year": 2014
    },
    {
      "playerID": "kolson1",
      "firstName": "Kane",
      "lastName": "Olson",
      "teamID": "revolution",
      "active": false,
      "jerseyNumber": "",
      "year": 2014
    },
    {
      "playerID": "kpettitsc",
      "firstName": "Kevin",
      "lastName": "Pettit-Scantling",
      "teamID": "radicals",
      "active": false,
      "jerseyNumber": "",
      "year": 2014
    },
    {
      "playerID": "kplew",
      "firstName": "Keenan",
      "lastName": "Plew",
      "teamID": "alleycats",
      "active": false,
      "jerseyNumber": "",
      "year": 2014
    },
    {
      "playerID": "kquinlan",
      "firstName": "Kevin",
      "lastName": "Quinlan",
      "teamID": "dragons",
      "active": false,
      "jerseyNumber": "",
      "year": 2014
    },
    {
      "playerID": "kseiler",
      "firstName": "Kevin",
      "lastName": "Seiler",
      "teamID": "windchill",
      "active": false,
      "jerseyNumber": "",
      "year": 2014
    },
    {
      "playerID": "ksmith1",
      "firstName": "Kevin",
      "lastName": "Smith",
      "teamID": "spiders",
      "active": false,
      "jerseyNumber": "",
      "year": 2014
    },
    {
      "playerID": "kthomson",
      "firstName": "Kris",
      "lastName": "Thomson",
      "teamID": "spiders",
      "active": false,
      "jerseyNumber": "",
      "year": 2014
    },
    {
      "playerID": "kvenose",
      "firstName": "Kevin",
      "lastName": "Venose",
      "teamID": "empire",
      "active": false,
      "jerseyNumber": "",
      "year": 2014
    },
    {
      "playerID": "kwells",
      "firstName": "Ken",
      "lastName": "Wells",
      "teamID": "phoenix",
      "active": false,
      "jerseyNumber": "",
      "year": 2014
    },
    {
      "playerID": "kwolf",
      "firstName": "Kyle",
      "lastName": "Wolf",
      "teamID": "phoenix",
      "active": false,
      "jerseyNumber": "",
      "year": 2014
    },
    {
      "playerID": "lbradford",
      "firstName": "Liam",
      "lastName": "Bradford",
      "teamID": "rush",
      "active": false,
      "jerseyNumber": "",
      "year": 2014
    },
    {
      "playerID": "lbroderic",
      "firstName": "Luke",
      "lastName": "Broderick",
      "teamID": "alleycats",
      "active": false,
      "jerseyNumber": "",
      "year": 2014
    },
    {
      "playerID": "ldallmann",
      "firstName": "Lucas",
      "lastName": "Dallmann",
      "teamID": "flamethrowers",
      "active": false,
      "jerseyNumber": "",
      "year": 2014
    },
    {
      "playerID": "ljacobs",
      "firstName": "Levi",
      "lastName": "Jacobs",
      "teamID": "alleycats",
      "active": false,
      "jerseyNumber": "",
      "year": 2014
    },
    {
      "playerID": "ljesperse",
      "firstName": "Luke",
      "lastName": "Jespersen",
      "teamID": "cascades",
      "active": false,
      "jerseyNumber": "",
      "year": 2014
    },
    {
      "playerID": "lrhyne",
      "firstName": "Logan",
      "lastName": "Rhyne",
      "teamID": "breeze",
      "active": false,
      "jerseyNumber": "",
      "year": 2014
    },
    {
      "playerID": "lshramko",
      "firstName": "Liam",
      "lastName": "Shramko",
      "teamID": "breeze",
      "active": false,
      "jerseyNumber": "",
      "year": 2014
    },
    {
      "playerID": "lstagg",
      "firstName": "Logan",
      "lastName": "Stagg",
      "teamID": "mechanix",
      "active": false,
      "jerseyNumber": "",
      "year": 2014
    },
    {
      "playerID": "lweiss",
      "firstName": "Logan",
      "lastName": "Weiss",
      "teamID": "windchill",
      "active": false,
      "jerseyNumber": "",
      "year": 2014
    },
    {
      "playerID": "lwininger",
      "firstName": "Lionel",
      "lastName": "Wininger",
      "teamID": "empire",
      "active": false,
      "jerseyNumber": "",
      "year": 2014
    },
    {
      "playerID": "lyoung",
      "firstName": "Lucas",
      "lastName": "Young",
      "teamID": "flamethrowers",
      "active": false,
      "jerseyNumber": "",
      "year": 2014
    },
    {
      "playerID": "mames",
      "firstName": "Michael",
      "lastName": "Ames",
      "teamID": "revolution",
      "active": false,
      "jerseyNumber": "",
      "year": 2014
    },
    {
      "playerID": "manderson",
      "firstName": "Matt",
      "lastName": "Anderson",
      "teamID": "dragons",
      "active": false,
      "jerseyNumber": "",
      "year": 2014
    },
    {
      "playerID": "mauletta",
      "firstName": "Matt",
      "lastName": "Auletta",
      "teamID": "empire",
      "active": false,
      "jerseyNumber": "",
      "year": 2014
    },
    {
      "playerID": "mbode",
      "firstName": "Matt",
      "lastName": "Bode",
      "teamID": "empire",
      "active": false,
      "jerseyNumber": "",
      "year": 2014
    },
    {
      "playerID": "mbordelea",
      "firstName": "Mathieu",
      "lastName": "Bordeleau",
      "teamID": "royal",
      "active": false,
      "jerseyNumber": "",
      "year": 2014
    },
    {
      "playerID": "mcavanaug",
      "firstName": "Michael",
      "lastName": "Cavanaugh",
      "teamID": "cascades",
      "active": false,
      "jerseyNumber": "",
      "year": 2014
    },
    {
      "playerID": "mdrost",
      "firstName": "Mike",
      "lastName": "Drost",
      "teamID": "empire",
      "active": false,
      "jerseyNumber": "",
      "year": 2014
    },
    {
      "playerID": "megan",
      "firstName": "Michael",
      "lastName": "Egan",
      "teamID": "union",
      "active": false,
      "jerseyNumber": "",
      "year": 2014
    },
    {
      "playerID": "melbogen",
      "firstName": "Mark",
      "lastName": "Elbogen",
      "teamID": "spiders",
      "active": false,
      "jerseyNumber": "",
      "year": 2014
    },
    {
      "playerID": "mfedorenk",
      "firstName": "Mark",
      "lastName": "Fedorenko",
      "teamID": "revolution",
      "active": false,
      "jerseyNumber": "",
      "year": 2014
    },
    {
      "playerID": "mford",
      "firstName": "Michael",
      "lastName": "Ford",
      "teamID": "revolution",
      "active": false,
      "jerseyNumber": "",
      "year": 2014
    },
    {
      "playerID": "mgottlieb",
      "firstName": "Mads",
      "lastName": "Gottlieb",
      "teamID": "riptide",
      "active": false,
      "jerseyNumber": "",
      "year": 2014
    },
    {
      "playerID": "mguy",
      "firstName": "Max",
      "lastName": "Guy",
      "teamID": "royal",
      "active": false,
      "jerseyNumber": "",
      "year": 2014
    },
    {
      "playerID": "mharvey",
      "firstName": "Matt",
      "lastName": "Harvey",
      "teamID": "riptide",
      "active": false,
      "jerseyNumber": "",
      "year": 2014
    },
    {
      "playerID": "mjones",
      "firstName": "Michael",
      "lastName": "Jones",
      "teamID": "rush",
      "active": false,
      "jerseyNumber": "",
      "year": 2014
    },
    {
      "playerID": "mjones1",
      "firstName": "Monte",
      "lastName": "Jones",
      "teamID": "mechanix",
      "active": false,
      "jerseyNumber": "",
      "year": 2014
    },
    {
      "playerID": "mking",
      "firstName": "Matthew",
      "lastName": "King",
      "teamID": "cascades",
      "active": false,
      "jerseyNumber": "",
      "year": 2014
    },
    {
      "playerID": "mkiyoi",
      "firstName": "Michael",
      "lastName": "Kiyoi",
      "teamID": "spiders",
      "active": false,
      "jerseyNumber": "",
      "year": 2014
    },
    {
      "playerID": "mlemar",
      "firstName": "Matt",
      "lastName": "LeMar",
      "teamID": "empire",
      "active": false,
      "jerseyNumber": "",
      "year": 2014
    },
    {
      "playerID": "mlin",
      "firstName": "Mark",
      "lastName": "Lin",
      "teamID": "breeze",
      "active": false,
      "jerseyNumber": "",
      "year": 2014
    },
    {
      "playerID": "mlloyd",
      "firstName": "Mark",
      "lastName": "Lloyd",
      "teamID": "rush",
      "active": false,
      "jerseyNumber": "",
      "year": 2014
    },
    {
      "playerID": "mmansfiel",
      "firstName": "Mike",
      "lastName": "Mansfield",
      "teamID": "mechanix",
      "active": false,
      "jerseyNumber": "",
      "year": 2014
    },
    {
      "playerID": "mmcclain",
      "firstName": "Mike",
      "lastName": "McClain",
      "teamID": "alleycats",
      "active": false,
      "jerseyNumber": "",
      "year": 2014
    },
    {
      "playerID": "mmuhlenka",
      "firstName": "Matt",
      "lastName": "Muhlenkamp",
      "teamID": "revolution",
      "active": false,
      "jerseyNumber": "",
      "year": 2014
    },
    {
      "playerID": "mnatali",
      "firstName": "Matthew",
      "lastName": "Natali",
      "teamID": "spiders",
      "active": false,
      "jerseyNumber": "",
      "year": 2014
    },
    {
      "playerID": "mneeley",
      "firstName": "Matthew",
      "lastName": "Neeley",
      "teamID": "cascades",
      "active": false,
      "jerseyNumber": "",
      "year": 2014
    },
    {
      "playerID": "mpeltier",
      "firstName": "Mat",
      "lastName": "Peltier",
      "teamID": "mechanix",
      "active": false,
      "jerseyNumber": "",
      "year": 2014
    },
    {
      "playerID": "mpetersen",
      "firstName": "Michael",
      "lastName": "Petersen",
      "teamID": "windchill",
      "active": false,
      "jerseyNumber": "",
      "year": 2014
    },
    {
      "playerID": "mpisansky",
      "firstName": "Marc",
      "lastName": "Pisansky",
      "teamID": "windchill",
      "active": false,
      "jerseyNumber": "",
      "year": 2014
    },
    {
      "playerID": "mradhe",
      "firstName": "Matthew",
      "lastName": "Radhe",
      "teamID": "breeze",
      "active": false,
      "jerseyNumber": "",
      "year": 2014
    },
    {
      "playerID": "mreeves",
      "firstName": "Mike",
      "lastName": "Reeves",
      "teamID": "phoenix",
      "active": false,
      "jerseyNumber": "",
      "year": 2014
    },
    {
      "playerID": "mrick",
      "firstName": "Maxwell",
      "lastName": "Rick",
      "teamID": "dragons",
      "active": false,
      "jerseyNumber": "",
      "year": 2014
    },
    {
      "playerID": "mrybak",
      "firstName": "Matt",
      "lastName": "Rybak",
      "teamID": "dragons",
      "active": false,
      "jerseyNumber": "",
      "year": 2014
    },
    {
      "playerID": "msanchez",
      "firstName": "Marcelo",
      "lastName": "Sanchez",
      "teamID": "spiders",
      "active": false,
      "jerseyNumber": "",
      "year": 2014
    },
    {
      "playerID": "msoldini",
      "firstName": "Marc",
      "lastName": "Soldini",
      "teamID": "mechanix",
      "active": false,
      "jerseyNumber": "",
      "year": 2014
    },
    {
      "playerID": "msteiner",
      "firstName": "Mitchell",
      "lastName": "Steiner",
      "teamID": "dragons",
      "active": false,
      "jerseyNumber": "",
      "year": 2014
    },
    {
      "playerID": "mstevens",
      "firstName": "Matt",
      "lastName": "Stevens",
      "teamID": "empire",
      "active": false,
      "jerseyNumber": "",
      "year": 2014
    },
    {
      "playerID": "mswain",
      "firstName": "Mike",
      "lastName": "Swain",
      "teamID": "radicals",
      "active": false,
      "jerseyNumber": "",
      "year": 2014
    },
    {
      "playerID": "mweber",
      "firstName": "Matt",
      "lastName": "Weber",
      "teamID": "radicals",
      "active": false,
      "jerseyNumber": "",
      "year": 2014
    },
    {
      "playerID": "mweber1",
      "firstName": "Michael",
      "lastName": "Weber",
      "teamID": "mechanix",
      "active": false,
      "jerseyNumber": "",
      "year": 2014
    },
    {
      "playerID": "mwheeler",
      "firstName": "Mitch",
      "lastName": "Wheeler",
      "teamID": "dragons",
      "active": false,
      "jerseyNumber": "",
      "year": 2014
    },
    {
      "playerID": "mwilson",
      "firstName": "Matthew",
      "lastName": "Wilson",
      "teamID": "lions",
      "active": false,
      "jerseyNumber": "",
      "year": 2014
    },
    {
      "playerID": "mwoolley",
      "firstName": "Michael",
      "lastName": "Woolley",
      "teamID": "lions",
      "active": false,
      "jerseyNumber": "",
      "year": 2014
    },
    {
      "playerID": "myoung",
      "firstName": "Matt",
      "lastName": "Young",
      "teamID": "windchill",
      "active": false,
      "jerseyNumber": "",
      "year": 2014
    },
    {
      "playerID": "mzimmerl",
      "firstName": "Mark",
      "lastName": "Zimmerl",
      "teamID": "royal",
      "active": false,
      "jerseyNumber": "",
      "year": 2014
    },
    {
      "playerID": "nbhakta",
      "firstName": "Nikhal",
      "lastName": "Bhakta",
      "teamID": "windchill",
      "active": false,
      "jerseyNumber": "",
      "year": 2014
    },
    {
      "playerID": "nbissonne",
      "firstName": "Nick",
      "lastName": "BIssonnette",
      "teamID": "revolution",
      "active": false,
      "jerseyNumber": "",
      "year": 2014
    },
    {
      "playerID": "nbosscher",
      "firstName": "Nate",
      "lastName": "Bosscher",
      "teamID": "spiders",
      "active": false,
      "jerseyNumber": "",
      "year": 2014
    },
    {
      "playerID": "nbotti",
      "firstName": "Nate",
      "lastName": "Botti",
      "teamID": "revolution",
      "active": false,
      "jerseyNumber": "",
      "year": 2014
    },
    {
      "playerID": "nbrochu",
      "firstName": "Nicolas",
      "lastName": "Brochu",
      "teamID": "royal",
      "active": false,
      "jerseyNumber": "",
      "year": 2014
    },
    {
      "playerID": "nbutler",
      "firstName": "Neal",
      "lastName": "Butler",
      "teamID": "dragons",
      "active": false,
      "jerseyNumber": "",
      "year": 2014
    },
    {
      "playerID": "ndare",
      "firstName": "Nick",
      "lastName": "Dare",
      "teamID": "cascades",
      "active": false,
      "jerseyNumber": "",
      "year": 2014
    },
    {
      "playerID": "nhanke",
      "firstName": "Neal",
      "lastName": "Hanke",
      "teamID": "windchill",
      "active": false,
      "jerseyNumber": "",
      "year": 2014
    },
    {
      "playerID": "nhutton",
      "firstName": "Nick",
      "lastName": "Hutton",
      "teamID": "alleycats",
      "active": false,
      "jerseyNumber": "",
      "year": 2014
    },
    {
      "playerID": "nmostaghi",
      "firstName": "Nima",
      "lastName": "Mostaghim",
      "teamID": "rush",
      "active": false,
      "jerseyNumber": "",
      "year": 2014
    },
    {
      "playerID": "nnarayan",
      "firstName": "Neil",
      "lastName": "Narayan",
      "teamID": "revolution",
      "active": false,
      "jerseyNumber": "",
      "year": 2014
    },
    {
      "playerID": "npage",
      "firstName": "Nate",
      "lastName": "Page",
      "teamID": "alleycats",
      "active": false,
      "jerseyNumber": "",
      "year": 2014
    },
    {
      "playerID": "nphelps",
      "firstName": "Neal",
      "lastName": "Phelps",
      "teamID": "union",
      "active": false,
      "jerseyNumber": "",
      "year": 2014
    },
    {
      "playerID": "nraisch",
      "firstName": "Nick",
      "lastName": "Raisch",
      "teamID": "spiders",
      "active": false,
      "jerseyNumber": "",
      "year": 2014
    },
    {
      "playerID": "nsaul",
      "firstName": "Noah",
      "lastName": "Saul",
      "teamID": "empire",
      "active": false,
      "jerseyNumber": "",
      "year": 2014
    },
    {
      "playerID": "nsimonell",
      "firstName": "Nicholas",
      "lastName": "Simonelli",
      "teamID": "windchill",
      "active": false,
      "jerseyNumber": "",
      "year": 2014
    },
    {
      "playerID": "nslovan",
      "firstName": "Nick",
      "lastName": "Slovan",
      "teamID": "flamethrowers",
      "active": false,
      "jerseyNumber": "",
      "year": 2014
    },
    {
      "playerID": "nthibedea",
      "firstName": "Nate",
      "lastName": "Thibedeau",
      "teamID": "radicals",
      "active": false,
      "jerseyNumber": "",
      "year": 2014
    },
    {
      "playerID": "nvanasse",
      "firstName": "Nicolas",
      "lastName": "Vanasse",
      "teamID": "royal",
      "active": false,
      "jerseyNumber": "",
      "year": 2014
    },
    {
      "playerID": "nvolkman",
      "firstName": "Nate",
      "lastName": "Volkman",
      "teamID": "radicals",
      "active": false,
      "jerseyNumber": "",
      "year": 2014
    },
    {
      "playerID": "nwetzel",
      "firstName": "Nick",
      "lastName": "Wetzel",
      "teamID": "revolution",
      "active": false,
      "jerseyNumber": "",
      "year": 2014
    },
    {
      "playerID": "nwhite",
      "firstName": "Nathan",
      "lastName": "White",
      "teamID": "spiders",
      "active": false,
      "jerseyNumber": "",
      "year": 2014
    },
    {
      "playerID": "odrouin",
      "firstName": "Olivier",
      "lastName": "Drouin",
      "teamID": "royal",
      "active": false,
      "jerseyNumber": "",
      "year": 2014
    },
    {
      "playerID": "panderson",
      "firstName": "Peter",
      "lastName": "Anderson",
      "teamID": "breeze",
      "active": false,
      "jerseyNumber": "",
      "year": 2014
    },
    {
      "playerID": "pbaylis",
      "firstName": "Patrick",
      "lastName": "Baylis",
      "teamID": "flamethrowers",
      "active": false,
      "jerseyNumber": "",
      "year": 2014
    },
    {
      "playerID": "pbender",
      "firstName": "Peter",
      "lastName": "Bender",
      "teamID": "cascades",
      "active": false,
      "jerseyNumber": "",
      "year": 2014
    },
    {
      "playerID": "pcarleton",
      "firstName": "Peter",
      "lastName": "Carleton",
      "teamID": "alleycats",
      "active": false,
      "jerseyNumber": "",
      "year": 2014
    },
    {
      "playerID": "pcarr",
      "firstName": "Pete",
      "lastName": "Carr",
      "teamID": "windchill",
      "active": false,
      "jerseyNumber": "",
      "year": 2014
    },
    {
      "playerID": "pcherosky",
      "firstName": "Phil",
      "lastName": "Cherosky",
      "teamID": "revolution",
      "active": false,
      "jerseyNumber": "",
      "year": 2014
    },
    {
      "playerID": "pgraffy",
      "firstName": "Peter",
      "lastName": "Graffy",
      "teamID": "radicals",
      "active": false,
      "jerseyNumber": "",
      "year": 2014
    },
    {
      "playerID": "phornberg",
      "firstName": "Philip",
      "lastName": "Hornberger",
      "teamID": "lions",
      "active": false,
      "jerseyNumber": "",
      "year": 2014
    },
    {
      "playerID": "pjensen",
      "firstName": "Pat",
      "lastName": "Jensen",
      "teamID": "windchill",
      "active": false,
      "jerseyNumber": "",
      "year": 2014
    },
    {
      "playerID": "pkaufmann",
      "firstName": "Patrick",
      "lastName": "Kaufmann",
      "teamID": "revolution",
      "active": false,
      "jerseyNumber": "",
      "year": 2014
    },
    {
      "playerID": "pkrantz",
      "firstName": "Patrick",
      "lastName": "Krantz",
      "teamID": "mechanix",
      "active": false,
      "jerseyNumber": "",
      "year": 2014
    },
    {
      "playerID": "plavertu",
      "firstName": "Pierre-Yves",
      "lastName": "Lavertu",
      "teamID": "riptide",
      "active": false,
      "jerseyNumber": "",
      "year": 2014
    },
    {
      "playerID": "pniles",
      "firstName": "Pat",
      "lastName": "Niles",
      "teamID": "windchill",
      "active": false,
      "jerseyNumber": "",
      "year": 2014
    },
    {
      "playerID": "posseward",
      "firstName": "Peter",
      "lastName": "Osseward",
      "teamID": "cascades",
      "active": false,
      "jerseyNumber": "",
      "year": 2014
    },
    {
      "playerID": "pshriwise",
      "firstName": "Pat",
      "lastName": "Shriwise",
      "teamID": "radicals",
      "active": false,
      "jerseyNumber": "",
      "year": 2014
    },
    {
      "playerID": "pstegemoe",
      "firstName": "Patrick",
      "lastName": "Stegemoeller",
      "teamID": "dragons",
      "active": false,
      "jerseyNumber": "",
      "year": 2014
    },
    {
      "playerID": "pthivierg",
      "firstName": "Philippe",
      "lastName": "Thivierge",
      "teamID": "royal",
      "active": false,
      "jerseyNumber": "",
      "year": 2014
    },
    {
      "playerID": "pwatanabe",
      "firstName": "Phil",
      "lastName": "Watanabe",
      "teamID": "rush",
      "active": false,
      "jerseyNumber": "",
      "year": 2014
    },
    {
      "playerID": "rartega",
      "firstName": "Renaldo",
      "lastName": "Artega",
      "teamID": "riptide",
      "active": false,
      "jerseyNumber": "",
      "year": 2014
    },
    {
      "playerID": "rbarr",
      "firstName": "Russ",
      "lastName": "Barr",
      "teamID": "lions",
      "active": false,
      "jerseyNumber": "",
      "year": 2014
    },
    {
      "playerID": "rcarver",
      "firstName": "Ryan",
      "lastName": "Carver",
      "teamID": "lions",
      "active": false,
      "jerseyNumber": "",
      "year": 2014
    },
    {
      "playerID": "rdrost",
      "firstName": "Ryan",
      "lastName": "Drost",
      "teamID": "empire",
      "active": false,
      "jerseyNumber": "",
      "year": 2014
    },
    {
      "playerID": "rforster",
      "firstName": "Ryan",
      "lastName": "Forster",
      "teamID": "phoenix",
      "active": false,
      "jerseyNumber": "",
      "year": 2014
    },
    {
      "playerID": "rgreenber",
      "firstName": "Rob",
      "lastName": "Greenberg",
      "teamID": "union",
      "active": false,
      "jerseyNumber": "",
      "year": 2014
    },
    {
      "playerID": "rgross",
      "firstName": "Rick",
      "lastName": "Gross",
      "teamID": "alleycats",
      "active": false,
      "jerseyNumber": "",
      "year": 2014
    },
    {
      "playerID": "rhahn",
      "firstName": "Ryan",
      "lastName": "Hahn",
      "teamID": "lions",
      "active": false,
      "jerseyNumber": "",
      "year": 2014
    },
    {
      "playerID": "rhowd",
      "firstName": "Russell",
      "lastName": "Howd",
      "teamID": "breeze",
      "active": false,
      "jerseyNumber": "",
      "year": 2014
    },
    {
      "playerID": "rjohnson",
      "firstName": "Robert",
      "lastName": "Johnson",
      "teamID": "windchill",
      "active": false,
      "jerseyNumber": "",
      "year": 2014
    },
    {
      "playerID": "rkawaoka",
      "firstName": "Ryo",
      "lastName": "Kawaoka",
      "teamID": "flamethrowers",
      "active": false,
      "jerseyNumber": "",
      "year": 2014
    },
    {
      "playerID": "rkubalanz",
      "firstName": "Ron",
      "lastName": "Kubalanza",
      "teamID": "union",
      "active": false,
      "jerseyNumber": "",
      "year": 2014
    },
    {
      "playerID": "rlee",
      "firstName": "Ryan",
      "lastName": "Lee",
      "teamID": "riptide",
      "active": false,
      "jerseyNumber": "",
      "year": 2014
    },
    {
      "playerID": "rnam",
      "firstName": "Ryan",
      "lastName": "Nam",
      "teamID": "breeze",
      "active": false,
      "jerseyNumber": "",
      "year": 2014
    },
    {
      "playerID": "rojo",
      "firstName": "Remi",
      "lastName": "Ojo",
      "teamID": "rush",
      "active": false,
      "jerseyNumber": "",
      "year": 2014
    },
    {
      "playerID": "rosborn",
      "firstName": "Ross",
      "lastName": "Osborn",
      "teamID": "mechanix",
      "active": false,
      "jerseyNumber": "",
      "year": 2014
    },
    {
      "playerID": "rsegal",
      "firstName": "Ryan",
      "lastName": "Segal",
      "teamID": "lions",
      "active": false,
      "jerseyNumber": "",
      "year": 2014
    },
    {
      "playerID": "rsmith1",
      "firstName": "Rob",
      "lastName": "Smith",
      "teamID": "dragons",
      "active": false,
      "jerseyNumber": "",
      "year": 2014
    },
    {
      "playerID": "rsturm",
      "firstName": "Ryan",
      "lastName": "Sturm",
      "teamID": "cascades",
      "active": false,
      "jerseyNumber": "",
      "year": 2014
    },
    {
      "playerID": "rsun",
      "firstName": "Ryan",
      "lastName": "Sun",
      "teamID": "riptide",
      "active": false,
      "jerseyNumber": "",
      "year": 2014
    },
    {
      "playerID": "rszeto",
      "firstName": "Ricky",
      "lastName": "Szeto",
      "teamID": "rush",
      "active": false,
      "jerseyNumber": "",
      "year": 2014
    },
    {
      "playerID": "rtam",
      "firstName": "Richard",
      "lastName": "Tam",
      "teamID": "riptide",
      "active": false,
      "jerseyNumber": "",
      "year": 2014
    },
    {
      "playerID": "rward",
      "firstName": "Ross",
      "lastName": "Ward",
      "teamID": "empire",
      "active": false,
      "jerseyNumber": "",
      "year": 2014
    },
    {
      "playerID": "rwharton",
      "firstName": "Rob",
      "lastName": "Wharton",
      "teamID": "revolution",
      "active": false,
      "jerseyNumber": "",
      "year": 2014
    },
    {
      "playerID": "sarmitage",
      "firstName": "Steve",
      "lastName": "Armitage",
      "teamID": "rush",
      "active": false,
      "jerseyNumber": "",
      "year": 2014
    },
    {
      "playerID": "sbrown",
      "firstName": "Spencer",
      "lastName": "Brown",
      "teamID": "lions",
      "active": false,
      "jerseyNumber": "",
      "year": 2014
    },
    {
      "playerID": "sbrunner",
      "firstName": "Skylar",
      "lastName": "Brunner",
      "teamID": "dragons",
      "active": false,
      "jerseyNumber": "",
      "year": 2014
    },
    {
      "playerID": "sburningh",
      "firstName": "Seokhee",
      "lastName": "Burningham",
      "teamID": "lions",
      "active": false,
      "jerseyNumber": "",
      "year": 2014
    },
    {
      "playerID": "scanetti",
      "firstName": "Seth",
      "lastName": "Canetti",
      "teamID": "empire",
      "active": false,
      "jerseyNumber": "",
      "year": 2014
    },
    {
      "playerID": "schang",
      "firstName": "Steven",
      "lastName": "Chang",
      "teamID": "spiders",
      "active": false,
      "jerseyNumber": "",
      "year": 2014
    },
    {
      "playerID": "schattert",
      "firstName": "Sam",
      "lastName": "Chatterton-Kirchmeier",
      "teamID": "flamethrowers",
      "active": false,
      "jerseyNumber": "",
      "year": 2014
    },
    {
      "playerID": "schilders",
      "firstName": "Sean",
      "lastName": "Childers",
      "teamID": "empire",
      "active": false,
      "jerseyNumber": "",
      "year": 2014
    },
    {
      "playerID": "sdonnella",
      "firstName": "Sean",
      "lastName": "Donnellan",
      "teamID": "dragons",
      "active": false,
      "jerseyNumber": "",
      "year": 2014
    },
    {
      "playerID": "sesser",
      "firstName": "Sam",
      "lastName": "Esser",
      "teamID": "phoenix",
      "active": false,
      "jerseyNumber": "",
      "year": 2014
    },
    {
      "playerID": "sfrazee",
      "firstName": "Sonny",
      "lastName": "Frazee",
      "teamID": "dragons",
      "active": false,
      "jerseyNumber": "",
      "year": 2014
    },
    {
      "playerID": "sfroebe",
      "firstName": "Shane",
      "lastName": "Froebe",
      "teamID": "lions",
      "active": false,
      "jerseyNumber": "",
      "year": 2014
    },
    {
      "playerID": "shiggins",
      "firstName": "Simon",
      "lastName": "Higgins",
      "teamID": "spiders",
      "active": false,
      "jerseyNumber": "",
      "year": 2014
    },
    {
      "playerID": "shightshu",
      "firstName": "Steven",
      "lastName": "Hightshue",
      "teamID": "alleycats",
      "active": false,
      "jerseyNumber": "",
      "year": 2014
    },
    {
      "playerID": "shohenste",
      "firstName": "Shane",
      "lastName": "Hohenstein",
      "teamID": "windchill",
      "active": false,
      "jerseyNumber": "",
      "year": 2014
    },
    {
      "playerID": "shoy",
      "firstName": "Samson",
      "lastName": "Hoy",
      "teamID": "riptide",
      "active": false,
      "jerseyNumber": "",
      "year": 2014
    },
    {
      "playerID": "skanner",
      "firstName": "Sam",
      "lastName": "Kanner",
      "teamID": "flamethrowers",
      "active": false,
      "jerseyNumber": "",
      "year": 2014
    },
    {
      "playerID": "sloscar",
      "firstName": "Spencer",
      "lastName": "Loscar",
      "teamID": "alleycats",
      "active": false,
      "jerseyNumber": "",
      "year": 2014
    },
    {
      "playerID": "smance",
      "firstName": "Stephane",
      "lastName": "Mance",
      "teamID": "union",
      "active": false,
      "jerseyNumber": "",
      "year": 2014
    },
    {
      "playerID": "smeyer",
      "firstName": "Seth",
      "lastName": "Meyer",
      "teamID": "radicals",
      "active": false,
      "jerseyNumber": "",
      "year": 2014
    },
    {
      "playerID": "smorgan",
      "firstName": "Sam",
      "lastName": "Morgan",
      "teamID": "phoenix",
      "active": false,
      "jerseyNumber": "",
      "year": 2014
    },
    {
      "playerID": "smott",
      "firstName": "Sean",
      "lastName": "Mott",
      "teamID": "phoenix",
      "active": false,
      "jerseyNumber": "",
      "year": 2014
    },
    {
      "playerID": "snaji",
      "firstName": "Steven",
      "lastName": "Naji",
      "teamID": "alleycats",
      "active": false,
      "jerseyNumber": "",
      "year": 2014
    },
    {
      "playerID": "sng",
      "firstName": "Stephen",
      "lastName": "Ng",
      "teamID": "phoenix",
      "active": false,
      "jerseyNumber": "",
      "year": 2014
    },
    {
      "playerID": "spoulos",
      "firstName": "Stephen",
      "lastName": "Poulos",
      "teamID": "empire",
      "active": false,
      "jerseyNumber": "",
      "year": 2014
    },
    {
      "playerID": "sraina",
      "firstName": "Sachin",
      "lastName": "Raina",
      "teamID": "rush",
      "active": false,
      "jerseyNumber": "",
      "year": 2014
    },
    {
      "playerID": "sredding",
      "firstName": "Schuyler",
      "lastName": "Redding",
      "teamID": "phoenix",
      "active": false,
      "jerseyNumber": "",
      "year": 2014
    },
    {
      "playerID": "srichgels",
      "firstName": "Scott",
      "lastName": "Richgels",
      "teamID": "radicals",
      "active": false,
      "jerseyNumber": "",
      "year": 2014
    },
    {
      "playerID": "sroeder",
      "firstName": "Scott",
      "lastName": "Roeder",
      "teamID": "spiders",
      "active": false,
      "jerseyNumber": "",
      "year": 2014
    },
    {
      "playerID": "srosso",
      "firstName": "Stephen",
      "lastName": "Rosso",
      "teamID": "phoenix",
      "active": false,
      "jerseyNumber": "",
      "year": 2014
    },
    {
      "playerID": "sstjeanti",
      "firstName": "Shawn",
      "lastName": "St-Jean Timmins",
      "teamID": "royal",
      "active": false,
      "jerseyNumber": "",
      "year": 2014
    },
    {
      "playerID": "staylor",
      "firstName": "Sam",
      "lastName": "Taylor",
      "teamID": "empire",
      "active": false,
      "jerseyNumber": "",
      "year": 2014
    },
    {
      "playerID": "strachtma",
      "firstName": "Sam",
      "lastName": "Trachtman",
      "teamID": "breeze",
      "active": false,
      "jerseyNumber": "",
      "year": 2014
    },
    {
      "playerID": "szaccaro",
      "firstName": "Sonny",
      "lastName": "Zaccaro",
      "teamID": "spiders",
      "active": false,
      "jerseyNumber": "",
      "year": 2014
    },
    {
      "playerID": "tadair",
      "firstName": "Tyrell",
      "lastName": "Adair",
      "teamID": "lions",
      "active": false,
      "jerseyNumber": "",
      "year": 2014
    },
    {
      "playerID": "tallen",
      "firstName": "Tom",
      "lastName": "Allen",
      "teamID": "phoenix",
      "active": false,
      "jerseyNumber": "",
      "year": 2014
    },
    {
      "playerID": "tannen",
      "firstName": "Tom",
      "lastName": "Annen",
      "teamID": "radicals",
      "active": false,
      "jerseyNumber": "",
      "year": 2014
    },
    {
      "playerID": "tbacon",
      "firstName": "Tyler",
      "lastName": "Bacon",
      "teamID": "spiders",
      "active": false,
      "jerseyNumber": "",
      "year": 2014
    },
    {
      "playerID": "tbloodwor",
      "firstName": "Tyler",
      "lastName": "Bloodworth",
      "teamID": "mechanix",
      "active": false,
      "jerseyNumber": "",
      "year": 2014
    },
    {
      "playerID": "tbrooks",
      "firstName": "Taylor",
      "lastName": "Brooks",
      "teamID": "empire",
      "active": false,
      "jerseyNumber": "",
      "year": 2014
    },
    {
      "playerID": "tburns",
      "firstName": "TJ",
      "lastName": "Burns",
      "teamID": "dragons",
      "active": false,
      "jerseyNumber": "",
      "year": 2014
    },
    {
      "playerID": "tcarpente",
      "firstName": "Travis",
      "lastName": "Carpenter",
      "teamID": "alleycats",
      "active": false,
      "jerseyNumber": "",
      "year": 2014
    },
    {
      "playerID": "tchamberl",
      "firstName": "Todd",
      "lastName": "Chamberlain",
      "teamID": "revolution",
      "active": false,
      "jerseyNumber": "",
      "year": 2014
    },
    {
      "playerID": "tchu",
      "firstName": "Ted",
      "lastName": "Chu",
      "teamID": "riptide",
      "active": false,
      "jerseyNumber": "",
      "year": 2014
    },
    {
      "playerID": "tcoolidge",
      "firstName": "Thomas",
      "lastName": "Coolidge",
      "teamID": "radicals",
      "active": false,
      "jerseyNumber": "",
      "year": 2014
    },
    {
      "playerID": "tdebyl",
      "firstName": "Tim",
      "lastName": "DeByl",
      "teamID": "radicals",
      "active": false,
      "jerseyNumber": "",
      "year": 2014
    },
    {
      "playerID": "tdegirola",
      "firstName": "Tyler",
      "lastName": "DeGirolamo",
      "teamID": "breeze",
      "active": false,
      "jerseyNumber": "",
      "year": 2014
    },
    {
      "playerID": "tfergus",
      "firstName": "Tim",
      "lastName": "Fergus",
      "teamID": "union",
      "active": false,
      "jerseyNumber": "",
      "year": 2014
    },
    {
      "playerID": "tgilligan",
      "firstName": "Tim",
      "lastName": "Gilligan",
      "teamID": "spiders",
      "active": false,
      "jerseyNumber": "",
      "year": 2014
    },
    {
      "playerID": "tgrace",
      "firstName": "Todd",
      "lastName": "Grace",
      "teamID": "revolution",
      "active": false,
      "jerseyNumber": "",
      "year": 2014
    },
    {
      "playerID": "tharper",
      "firstName": "Trevor",
      "lastName": "Harper",
      "teamID": "lions",
      "active": false,
      "jerseyNumber": "",
      "year": 2014
    },
    {
      "playerID": "thenry",
      "firstName": "Trevor",
      "lastName": "Henry",
      "teamID": "rush",
      "active": false,
      "jerseyNumber": "",
      "year": 2014
    },
    {
      "playerID": "thorvath",
      "firstName": "Thomas",
      "lastName": "Horvath",
      "teamID": "dragons",
      "active": false,
      "jerseyNumber": "",
      "year": 2014
    },
    {
      "playerID": "tknight",
      "firstName": "Travis",
      "lastName": "Knight",
      "teamID": "revolution",
      "active": false,
      "jerseyNumber": "",
      "year": 2014
    },
    {
      "playerID": "tkominos",
      "firstName": "Tim",
      "lastName": "Kominos",
      "teamID": "dragons",
      "active": false,
      "jerseyNumber": "",
      "year": 2014
    },
    {
      "playerID": "tkraemer",
      "firstName": "Taylor",
      "lastName": "Kraemer",
      "teamID": "union",
      "active": false,
      "jerseyNumber": "",
      "year": 2014
    },
    {
      "playerID": "tkunsa",
      "firstName": "Tyler",
      "lastName": "Kunsa",
      "teamID": "breeze",
      "active": false,
      "jerseyNumber": "",
      "year": 2014
    },
    {
      "playerID": "tlahey",
      "firstName": "Taylor",
      "lastName": "Lahey",
      "teamID": "flamethrowers",
      "active": false,
      "jerseyNumber": "",
      "year": 2014
    },
    {
      "playerID": "tlavis",
      "firstName": "Tim",
      "lastName": "Lavis",
      "teamID": "riptide",
      "active": false,
      "jerseyNumber": "",
      "year": 2014
    },
    {
      "playerID": "tmcknight",
      "firstName": "Thomson",
      "lastName": "McKnight",
      "teamID": "rush",
      "active": false,
      "jerseyNumber": "",
      "year": 2014
    },
    {
      "playerID": "tnadon",
      "firstName": "Taylor",
      "lastName": "Nadon",
      "teamID": "riptide",
      "active": false,
      "jerseyNumber": "",
      "year": 2014
    },
    {
      "playerID": "tpehrson",
      "firstName": "Tony",
      "lastName": "Pehrson",
      "teamID": "lions",
      "active": false,
      "jerseyNumber": "",
      "year": 2014
    },
    {
      "playerID": "trowe",
      "firstName": "Thomas",
      "lastName": "Rowe",
      "teamID": "riptide",
      "active": false,
      "jerseyNumber": "",
      "year": 2014
    },
    {
      "playerID": "tryan",
      "firstName": "Tim",
      "lastName": "Ryan",
      "teamID": "breeze",
      "active": false,
      "jerseyNumber": "",
      "year": 2014
    },
    {
      "playerID": "tsettles",
      "firstName": "Tim",
      "lastName": "Settles",
      "teamID": "revolution",
      "active": false,
      "jerseyNumber": "",
      "year": 2014
    },
    {
      "playerID": "ttsang",
      "firstName": "Tim",
      "lastName": "Tsang",
      "teamID": "royal",
      "active": false,
      "jerseyNumber": "",
      "year": 2014
    },
    {
      "playerID": "unknown12",
      "firstName": "Rob",
      "lastName": "S",
      "teamID": "union",
      "active": false,
      "jerseyNumber": "",
      "year": 2014
    },
    {
      "playerID": "unknown14",
      "firstName": "Brian",
      "lastName": "T",
      "teamID": "phoenix",
      "active": false,
      "jerseyNumber": "",
      "year": 2014
    },
    {
      "playerID": "unknown16",
      "firstName": "Dennis",
      "lastName": "M",
      "teamID": "empire",
      "active": false,
      "jerseyNumber": "",
      "year": 2014
    },
    {
      "playerID": "unknown17",
      "firstName": "Dylan",
      "lastName": "B",
      "teamID": "dragons",
      "active": false,
      "jerseyNumber": "",
      "year": 2014
    },
    {
      "playerID": "unknown18",
      "firstName": "James",
      "lastName": "O",
      "teamID": "cascades",
      "active": false,
      "jerseyNumber": "",
      "year": 2014
    },
    {
      "playerID": "unknown19",
      "firstName": "John",
      "lastName": "I",
      "teamID": "empire",
      "active": false,
      "jerseyNumber": "",
      "year": 2014
    },
    {
      "playerID": "unknown21",
      "firstName": "Michael",
      "lastName": "A",
      "teamID": "empire",
      "active": false,
      "jerseyNumber": "",
      "year": 2014
    },
    {
      "playerID": "unknown22",
      "firstName": "Mike",
      "lastName": "K",
      "teamID": "flamethrowers",
      "active": false,
      "jerseyNumber": "",
      "year": 2014
    },
    {
      "playerID": "unknown23",
      "firstName": "Sasha",
      "lastName": "S",
      "teamID": "cascades",
      "active": false,
      "jerseyNumber": "",
      "year": 2014
    },
    {
      "playerID": "unknown24",
      "firstName": "Saul",
      "lastName": "H",
      "teamID": "lions",
      "active": false,
      "jerseyNumber": "",
      "year": 2014
    },
    {
      "playerID": "unknown25",
      "firstName": "Will",
      "lastName": "W",
      "teamID": "cascades",
      "active": false,
      "jerseyNumber": "",
      "year": 2014
    },
    {
      "playerID": "valanguil",
      "firstName": "Von",
      "lastName": "Alanguilan",
      "teamID": "union",
      "active": false,
      "jerseyNumber": "",
      "year": 2014
    },
    {
      "playerID": "wdrumrigh",
      "firstName": "Will",
      "lastName": "Drumright",
      "teamID": "alleycats",
      "active": false,
      "jerseyNumber": "",
      "year": 2014
    },
    {
      "playerID": "whoehne",
      "firstName": "William",
      "lastName": "Hoehne",
      "teamID": "phoenix",
      "active": false,
      "jerseyNumber": "",
      "year": 2014
    },
    {
      "playerID": "whuffer",
      "firstName": "Will",
      "lastName": "Huffer",
      "teamID": "revolution",
      "active": false,
      "jerseyNumber": "",
      "year": 2014
    },
    {
      "playerID": "wnelson",
      "firstName": "Walden",
      "lastName": "Nelson",
      "teamID": "union",
      "active": false,
      "jerseyNumber": "",
      "year": 2014
    },
    {
      "playerID": "wsloane",
      "firstName": "Will",
      "lastName": "Sloane",
      "teamID": "dragons",
      "active": false,
      "jerseyNumber": "",
      "year": 2014
    },
    {
      "playerID": "wvu",
      "firstName": "William",
      "lastName": "Vu",
      "teamID": "riptide",
      "active": false,
      "jerseyNumber": "",
      "year": 2014
    },
    {
      "playerID": "xtitcomb",
      "firstName": "Xtehn",
      "lastName": "Titcomb",
      "teamID": "union",
      "active": false,
      "jerseyNumber": "",
      "year": 2014
    },
    {
      "playerID": "ycabot",
      "firstName": "Yoland",
      "lastName": "Cabot",
      "teamID": "royal",
      "active": false,
      "jerseyNumber": "",
      "year": 2014
    },
    {
      "playerID": "zbarnhart",
      "firstName": "Zach",
      "lastName": "Barnhart",
      "teamID": "mechanix",
      "active": false,
      "jerseyNumber": "",
      "year": 2014
    },
    {
      "playerID": "zmaynard",
      "firstName": "Zach",
      "lastName": "Maynard",
      "teamID": "alleycats",
      "active": false,
      "jerseyNumber": "",
      "year": 2014
    },
    {
      "playerID": "zpurdy",
      "firstName": "Zack",
      "lastName": "Purdy",
      "teamID": "flamethrowers",
      "active": false,
      "jerseyNumber": "",
      "year": 2014
    },
    {
      "playerID": "zrankin",
      "firstName": "Zane",
      "lastName": "Rankin",
      "teamID": "flamethrowers",
      "active": false,
      "jerseyNumber": "",
      "year": 2014
    },
    {
      "playerID": "zsmith",
      "firstName": "Zack",
      "lastName": "Smith",
      "teamID": "dragons",
      "active": false,
      "jerseyNumber": "",
      "year": 2014
    },
    {
      "playerID": "ztravis",
      "firstName": "Zack",
      "lastName": "Travis",
      "teamID": "flamethrowers",
      "active": false,
      "jerseyNumber": "",
      "year": 2014
    }
  ]
}